[
  {
    "author": "LMB Studio",
    "link_thumb": "https://live.staticflickr.com/65535/51676181662_6990081209_o.gif",
    "link_bin": "https://github.com/lmbstudiocontact/mb6_6/raw/main/Kitty\u0026MyMelody1_M6_2.bin",
    "id_bin": "Kitty\u0026MyMelody1_M6_2",
    "list_language": [
      {
        "author": "LMB Studio",
        "link_thumb": "https://live.staticflickr.com/65535/51677867815_6efe88d9f1_o.gif",
        "link_bin": "https://github.com/lmbstudiocontact/mb6_6/raw/main/Kitty\u0026MyMelody1_M6_2_English.bin",
        "name_language": "Kitty\u0026MyMelody1_M6_2_English",
        "id_bin_language": "Kitty\u0026MyMelody1_M6_2_English"
      },
      {
        "author": "LMB Studio",
        "link_thumb": "https://live.staticflickr.com/65535/51677658244_16a6c09cac_o.gif",
        "link_bin": "https://github.com/lmbstudiocontact/mb6_6/raw/main/Kitty\u0026MyMelody1_M6_2_Portuguese.bin",
        "name_language": "Kitty\u0026MyMelody1_M6_2_Portuguese",
        "id_bin_language": "Kitty\u0026MyMelody1_M6_2_Portuguese"
      },
      {
        "author": "LMB Studio",
        "link_thumb": "https://live.staticflickr.com/65535/51676182657_0460fa968e_o.gif",
        "link_bin": "https://github.com/lmbstudiocontact/mb6_6/raw/main/Kitty\u0026MyMelody1_M6_2_Russian.bin",
        "name_language": "Kitty\u0026MyMelody1_M6_2_Russian",
        "id_bin_language": "Kitty\u0026MyMelody1_M6_2_Russian"
      },
      {
        "author": "LMB Studio",
        "link_thumb": "https://live.staticflickr.com/65535/51676182907_29401fda6a_o.gif",
        "link_bin": "https://github.com/lmbstudiocontact/mb6_6/raw/main/Kitty\u0026MyMelody1_M6_2_Spanish.bin",
        "name_language": "Kitty\u0026MyMelody1_M6_2_Spanish",
        "id_bin_language": "Kitty\u0026MyMelody1_M6_2_Spanish"
      }
    ],
    "array_tags": [],
    "list_album": [
      {
        "id_album": "1352454006",
        "link_thumb": "https://live.staticflickr.com/65535/51676181662_6990081209_o.gif",
        "title": "Kitty \u0026 My Melody_M6_2"
      }
    ]
  },
  {
    "author": "LMB Studio",
    "link_thumb": "https://live.staticflickr.com/65535/51678113170_f0734b659e_o.gif",
    "link_bin": "https://github.com/lmbstudiocontact/mb6_3/raw/main/OnePieceAnime109_M6_2.bin",
    "id_bin": "OnePieceAnime109_M6_2",
    "list_language": [
      {
        "author": "LMB Studio",
        "link_thumb": "https://live.staticflickr.com/65535/51676426802_0cf7a26716_o.gif",
        "link_bin": "https://github.com/lmbstudiocontact/mb6_3/raw/main/OnePieceAnime109_M6_2_English.bin",
        "name_language": "OnePieceAnime109_M6_2_English",
        "id_bin_language": "OnePieceAnime109_M6_2_English"
      },
      {
        "author": "LMB Studio",
        "link_thumb": "https://live.staticflickr.com/65535/51677480628_bdf32448cf_o.gif",
        "link_bin": "https://github.com/lmbstudiocontact/mb6_3/raw/main/OnePieceAnime109_M6_2_Portuguese.bin",
        "name_language": "OnePieceAnime109_M6_2_Portuguese",
        "id_bin_language": "OnePieceAnime109_M6_2_Portuguese"
      },
      {
        "author": "LMB Studio",
        "link_thumb": "https://live.staticflickr.com/65535/51677905659_69338ffc8a_o.gif",
        "link_bin": "https://github.com/lmbstudiocontact/mb6_3/raw/main/OnePieceAnime109_M6_2_Russian.bin",
        "name_language": "OnePieceAnime109_M6_2_Russian",
        "id_bin_language": "OnePieceAnime109_M6_2_Russian"
      },
      {
        "author": "LMB Studio",
        "link_thumb": "https://live.staticflickr.com/65535/51678114005_80355ea9bc_o.gif",
        "link_bin": "https://github.com/lmbstudiocontact/mb6_3/raw/main/OnePieceAnime109_M6_2_Spanish.bin",
        "name_language": "OnePieceAnime109_M6_2_Spanish",
        "id_bin_language": "OnePieceAnime109_M6_2_Spanish"
      }
    ],
    "array_tags": [],
    "list_album": [
      {
        "id_album": "1669710643",
        "link_thumb": "https://live.staticflickr.com/65535/51678113170_f0734b659e_o.gif",
        "title": "One Piece Anime_M6_2"
      }
    ]
  },
  {
    "author": "LMB Studio",
    "link_thumb": "https://live.staticflickr.com/65535/51677160096_630003ff7a_o.gif",
    "link_bin": "https://github.com/lmbstudiocontact/mb6_7/raw/main/Music20_M6_2.bin",
    "id_bin": "Music20_M6_2",
    "list_language": [
      {
        "author": "LMB Studio",
        "link_thumb": "https://live.staticflickr.com/65535/51677408053_fbf9326050_o.gif",
        "link_bin": "https://github.com/lmbstudiocontact/mb6_7/raw/main/Music20_M6_2_English.bin",
        "name_language": "Music20_M6_2_English",
        "id_bin_language": "Music20_M6_2_English"
      },
      {
        "author": "LMB Studio",
        "link_thumb": "https://live.staticflickr.com/65535/51677408273_c1f079b702_o.gif",
        "link_bin": "https://github.com/lmbstudiocontact/mb6_7/raw/main/Music20_M6_2_Portuguese.bin",
        "name_language": "Music20_M6_2_Portuguese",
        "id_bin_language": "Music20_M6_2_Portuguese"
      },
      {
        "author": "LMB Studio",
        "link_thumb": "https://live.staticflickr.com/65535/51677408468_8246ca48d4_o.gif",
        "link_bin": "https://github.com/lmbstudiocontact/mb6_7/raw/main/Music20_M6_2_Russian.bin",
        "name_language": "Music20_M6_2_Russian",
        "id_bin_language": "Music20_M6_2_Russian"
      },
      {
        "author": "LMB Studio",
        "link_thumb": "https://live.staticflickr.com/65535/51676355447_f6be5f179a_o.gif",
        "link_bin": "https://github.com/lmbstudiocontact/mb6_7/raw/main/Music20_M6_2_Spanish.bin",
        "name_language": "Music20_M6_2_Spanish",
        "id_bin_language": "Music20_M6_2_Spanish"
      }
    ],
    "array_tags": [],
    "list_album": [
      {
        "id_album": "1212255478",
        "link_thumb": "https://live.staticflickr.com/65535/51677160096_630003ff7a_o.gif",
        "title": "Music_M6_2"
      }
    ]
  },
  {
    "author": "Samwinder_BR",
    "link_thumb": "https://live.staticflickr.com/65535/51669823256_a09b3a825b_o.gif",
    "link_bin": "https://github.com/lmbstudiocontact/mb6_1/raw/main/993.bin",
    "id_bin": "993",
    "list_language": [],
    "array_tags": [
      "space"
    ],
    "list_album": [
      {
        "id_album": "2433880",
        "link_thumb": "https://live.staticflickr.com/65535/51669823256_a09b3a825b_o.gif",
        "title": "None"
      }
    ]
  },
  {
    "author": "LMB Studio",
    "link_thumb": "https://live.staticflickr.com/65535/51676613233_9fb51148ab_o.gif",
    "link_bin": "https://github.com/lmbstudiocontact/mb6_8/raw/main/BossBabyCartoon1_M6_2.bin",
    "id_bin": "BossBabyCartoon1_M6_2",
    "list_language": [
      {
        "author": "LMB Studio",
        "link_thumb": "https://live.staticflickr.com/65535/51676613423_ff4f310746_o.gif",
        "link_bin": "https://github.com/lmbstudiocontact/mb6_8/raw/main/BossBabyCartoon1_M6_2_English.bin",
        "name_language": "BossBabyCartoon1_M6_2_English",
        "id_bin_language": "BossBabyCartoon1_M6_2_English"
      },
      {
        "author": "LMB Studio",
        "link_thumb": "https://live.staticflickr.com/65535/51677042429_338b2dee61_o.gif",
        "link_bin": "https://github.com/lmbstudiocontact/mb6_8/raw/main/BossBabyCartoon1_M6_2_Portuguese.bin",
        "name_language": "BossBabyCartoon1_M6_2_Portuguese",
        "id_bin_language": "BossBabyCartoon1_M6_2_Portuguese"
      },
      {
        "author": "LMB Studio",
        "link_thumb": "https://live.staticflickr.com/65535/51676613798_39163fd84e_o.gif",
        "link_bin": "https://github.com/lmbstudiocontact/mb6_8/raw/main/BossBabyCartoon1_M6_2_Russian.bin",
        "name_language": "BossBabyCartoon1_M6_2_Russian",
        "id_bin_language": "BossBabyCartoon1_M6_2_Russian"
      },
      {
        "author": "LMB Studio",
        "link_thumb": "https://live.staticflickr.com/65535/51677249205_73a6497b82_o.gif",
        "link_bin": "https://github.com/lmbstudiocontact/mb6_8/raw/main/BossBabyCartoon1_M6_2_Spanish.bin",
        "name_language": "BossBabyCartoon1_M6_2_Spanish",
        "id_bin_language": "BossBabyCartoon1_M6_2_Spanish"
      }
    ],
    "array_tags": [],
    "list_album": [
      {
        "id_album": "-2047829404",
        "link_thumb": "https://live.staticflickr.com/65535/51676613233_9fb51148ab_o.gif",
        "title": "Boss Baby Cartoon_M6_2"
      }
    ]
  },
  {
    "author": "marce2santos",
    "link_thumb": "https://live.staticflickr.com/65535/51670664915_668974bc1e_o.gif",
    "link_bin": "https://github.com/lmbstudiocontact/mb6_0/raw/main/816.bin",
    "id_bin": "816",
    "list_language": [],
    "array_tags": [],
    "list_album": [
      {
        "id_album": "2433880",
        "link_thumb": "https://live.staticflickr.com/65535/51670664915_668974bc1e_o.gif",
        "title": "None"
      }
    ]
  },
  {
    "author": "LMB Studio",
    "link_thumb": "https://live.staticflickr.com/65535/51677714580_336ebd19ff_o.gif",
    "link_bin": "https://github.com/lmbstudiocontact/mb6_6/raw/main/HalloweenGhostWitch17_M6_2.bin",
    "id_bin": "HalloweenGhostWitch17_M6_2",
    "list_language": [
      {
        "author": "LMB Studio",
        "link_thumb": "https://live.staticflickr.com/65535/51676831821_512545a2b1_o.gif",
        "link_bin": "https://github.com/lmbstudiocontact/mb6_6/raw/main/HalloweenGhostWitch17_M6_2_English.bin",
        "name_language": "HalloweenGhostWitch17_M6_2_English",
        "id_bin_language": "HalloweenGhostWitch17_M6_2_English"
      },
      {
        "author": "LMB Studio",
        "link_thumb": "https://live.staticflickr.com/65535/51677504294_73cff72b25_o.gif",
        "link_bin": "https://github.com/lmbstudiocontact/mb6_6/raw/main/HalloweenGhostWitch17_M6_2_Portuguese.bin",
        "name_language": "HalloweenGhostWitch17_M6_2_Portuguese",
        "id_bin_language": "HalloweenGhostWitch17_M6_2_Portuguese"
      },
      {
        "author": "LMB Studio",
        "link_thumb": "https://live.staticflickr.com/65535/51677715090_289a1f763e_o.gif",
        "link_bin": "https://github.com/lmbstudiocontact/mb6_6/raw/main/HalloweenGhostWitch17_M6_2_Russian.bin",
        "name_language": "HalloweenGhostWitch17_M6_2_Russian",
        "id_bin_language": "HalloweenGhostWitch17_M6_2_Russian"
      },
      {
        "author": "LMB Studio",
        "link_thumb": "https://live.staticflickr.com/65535/51677504694_c61fb2e510_o.gif",
        "link_bin": "https://github.com/lmbstudiocontact/mb6_6/raw/main/HalloweenGhostWitch17_M6_2_Spanish.bin",
        "name_language": "HalloweenGhostWitch17_M6_2_Spanish",
        "id_bin_language": "HalloweenGhostWitch17_M6_2_Spanish"
      }
    ],
    "array_tags": [],
    "list_album": [
      {
        "id_album": "-877220232",
        "link_thumb": "https://live.staticflickr.com/65535/51677714580_336ebd19ff_o.gif",
        "title": "Halloween Ghost Witch_M6_2"
      }
    ]
  },
  {
    "author": "LMB Studio",
    "link_thumb": "https://live.staticflickr.com/65535/51677161191_bbfe8239af_o.gif",
    "link_bin": "https://github.com/lmbstudiocontact/mb6_7/raw/main/Music21_M6_2.bin",
    "id_bin": "Music21_M6_2",
    "list_language": [
      {
        "author": "LMB Studio",
        "link_thumb": "https://live.staticflickr.com/65535/51677409133_4405b615b8_o.gif",
        "link_bin": "https://github.com/lmbstudiocontact/mb6_7/raw/main/Music21_M6_2_English.bin",
        "name_language": "Music21_M6_2_English",
        "id_bin_language": "Music21_M6_2_English"
      },
      {
        "author": "LMB Studio",
        "link_thumb": "https://live.staticflickr.com/65535/51677833799_df72b72d51_o.gif",
        "link_bin": "https://github.com/lmbstudiocontact/mb6_7/raw/main/Music21_M6_2_Portuguese.bin",
        "name_language": "Music21_M6_2_Portuguese",
        "id_bin_language": "Music21_M6_2_Portuguese"
      },
      {
        "author": "LMB Studio",
        "link_thumb": "https://live.staticflickr.com/65535/51677161776_5d617682fc_o.gif",
        "link_bin": "https://github.com/lmbstudiocontact/mb6_7/raw/main/Music21_M6_2_Russian.bin",
        "name_language": "Music21_M6_2_Russian",
        "id_bin_language": "Music21_M6_2_Russian"
      },
      {
        "author": "LMB Studio",
        "link_thumb": "https://live.staticflickr.com/65535/51678043895_98f5d66c75_o.gif",
        "link_bin": "https://github.com/lmbstudiocontact/mb6_7/raw/main/Music21_M6_2_Spanish.bin",
        "name_language": "Music21_M6_2_Spanish",
        "id_bin_language": "Music21_M6_2_Spanish"
      }
    ],
    "array_tags": [],
    "list_album": [
      {
        "id_album": "1212255478",
        "link_thumb": "https://live.staticflickr.com/65535/51677161191_bbfe8239af_o.gif",
        "title": "Music_M6_2"
      }
    ]
  },
  {
    "author": "LMB Studio",
    "link_thumb": "https://live.staticflickr.com/65535/51677479108_17a63f0165_o.gif",
    "link_bin": "https://github.com/lmbstudiocontact/mb6_3/raw/main/OnePieceAnime108_M6_2.bin",
    "id_bin": "OnePieceAnime108_M6_2",
    "list_language": [
      {
        "author": "LMB Studio",
        "link_thumb": "https://live.staticflickr.com/65535/51677904029_bc5a4c70cc_o.gif",
        "link_bin": "https://github.com/lmbstudiocontact/mb6_3/raw/main/OnePieceAnime108_M6_2_English.bin",
        "name_language": "OnePieceAnime108_M6_2_English",
        "id_bin_language": "OnePieceAnime108_M6_2_English"
      },
      {
        "author": "LMB Studio",
        "link_thumb": "https://live.staticflickr.com/65535/51677231816_245831e3ba_o.gif",
        "link_bin": "https://github.com/lmbstudiocontact/mb6_3/raw/main/OnePieceAnime108_M6_2_Portuguese.bin",
        "name_language": "OnePieceAnime108_M6_2_Portuguese",
        "id_bin_language": "OnePieceAnime108_M6_2_Portuguese"
      },
      {
        "author": "LMB Studio",
        "link_thumb": "https://live.staticflickr.com/65535/51678112610_d28cc6db14_o.gif",
        "link_bin": "https://github.com/lmbstudiocontact/mb6_3/raw/main/OnePieceAnime108_M6_2_Russian.bin",
        "name_language": "OnePieceAnime108_M6_2_Russian",
        "id_bin_language": "OnePieceAnime108_M6_2_Russian"
      },
      {
        "author": "LMB Studio",
        "link_thumb": "https://live.staticflickr.com/65535/51678112885_231bab1a46_o.gif",
        "link_bin": "https://github.com/lmbstudiocontact/mb6_3/raw/main/OnePieceAnime108_M6_2_Spanish.bin",
        "name_language": "OnePieceAnime108_M6_2_Spanish",
        "id_bin_language": "OnePieceAnime108_M6_2_Spanish"
      }
    ],
    "array_tags": [],
    "list_album": [
      {
        "id_album": "1669710643",
        "link_thumb": "https://live.staticflickr.com/65535/51677479108_17a63f0165_o.gif",
        "title": "One Piece Anime_M6_2"
      }
    ]
  },
  {
    "author": "LMB Studio",
    "link_thumb": "https://live.staticflickr.com/65535/51676434961_2f141d34ed_o.gif",
    "link_bin": "https://github.com/lmbstudiocontact/mb6_8/raw/main/CuteArt1_M6_2.bin",
    "id_bin": "CuteArt1_M6_2",
    "list_language": [
      {
        "author": "LMB Studio",
        "link_thumb": "https://live.staticflickr.com/65535/51675631187_cc927d8591_o.gif",
        "link_bin": "https://github.com/lmbstudiocontact/mb6_8/raw/main/CuteArt1_M6_2_English.bin",
        "name_language": "CuteArt1_M6_2_English",
        "id_bin_language": "CuteArt1_M6_2_English"
      },
      {
        "author": "LMB Studio",
        "link_thumb": "https://live.staticflickr.com/65535/51675631432_d30446553c_o.gif",
        "link_bin": "https://github.com/lmbstudiocontact/mb6_8/raw/main/CuteArt1_M6_2_Portuguese.bin",
        "name_language": "CuteArt1_M6_2_Portuguese",
        "id_bin_language": "CuteArt1_M6_2_Portuguese"
      },
      {
        "author": "LMB Studio",
        "link_thumb": "https://live.staticflickr.com/65535/51675631662_34a8696055_o.gif",
        "link_bin": "https://github.com/lmbstudiocontact/mb6_8/raw/main/CuteArt1_M6_2_Russian.bin",
        "name_language": "CuteArt1_M6_2_Russian",
        "id_bin_language": "CuteArt1_M6_2_Russian"
      },
      {
        "author": "LMB Studio",
        "link_thumb": "https://live.staticflickr.com/65535/51676680388_953559cb15_o.gif",
        "link_bin": "https://github.com/lmbstudiocontact/mb6_8/raw/main/CuteArt1_M6_2_Spanish.bin",
        "name_language": "CuteArt1_M6_2_Spanish",
        "id_bin_language": "CuteArt1_M6_2_Spanish"
      }
    ],
    "array_tags": [],
    "list_album": [
      {
        "id_album": "195512437",
        "link_thumb": "https://live.staticflickr.com/65535/51676434961_2f141d34ed_o.gif",
        "title": "Cute Art_M6_2"
      }
    ]
  },
  {
    "author": "LMB Studio",
    "link_thumb": "https://live.staticflickr.com/65535/51675682502_51edaa988a_o.gif",
    "link_bin": "https://github.com/lmbstudiocontact/mb6_8/raw/main/CuteArt5_M6_2.bin",
    "id_bin": "CuteArt5_M6_2",
    "list_language": [
      {
        "author": "LMB Studio",
        "link_thumb": "https://live.staticflickr.com/65535/51677158684_193670105e_o.gif",
        "link_bin": "https://github.com/lmbstudiocontact/mb6_8/raw/main/CuteArt5_M6_2_English.bin",
        "name_language": "CuteArt5_M6_2_English",
        "id_bin_language": "CuteArt5_M6_2_English"
      },
      {
        "author": "LMB Studio",
        "link_thumb": "https://live.staticflickr.com/65535/51675682977_c77064e9f0_o.gif",
        "link_bin": "https://github.com/lmbstudiocontact/mb6_8/raw/main/CuteArt5_M6_2_Portuguese.bin",
        "name_language": "CuteArt5_M6_2_Portuguese",
        "id_bin_language": "CuteArt5_M6_2_Portuguese"
      },
      {
        "author": "LMB Studio",
        "link_thumb": "https://live.staticflickr.com/65535/51677365140_22afc63aa0_o.gif",
        "link_bin": "https://github.com/lmbstudiocontact/mb6_8/raw/main/CuteArt5_M6_2_Russian.bin",
        "name_language": "CuteArt5_M6_2_Russian",
        "id_bin_language": "CuteArt5_M6_2_Russian"
      },
      {
        "author": "LMB Studio",
        "link_thumb": "https://live.staticflickr.com/65535/51677159469_e632565045_o.gif",
        "link_bin": "https://github.com/lmbstudiocontact/mb6_8/raw/main/CuteArt5_M6_2_Spanish.bin",
        "name_language": "CuteArt5_M6_2_Spanish",
        "id_bin_language": "CuteArt5_M6_2_Spanish"
      }
    ],
    "array_tags": [],
    "list_album": [
      {
        "id_album": "195512437",
        "link_thumb": "https://live.staticflickr.com/65535/51675682502_51edaa988a_o.gif",
        "title": "Cute Art_M6_2"
      }
    ]
  },
  {
    "author": "None",
    "link_thumb": "https://live.staticflickr.com/65535/51668717042_783718590c_o.gif",
    "link_bin": "https://github.com/lmbstudiocontact/mb6_0/raw/main/1465.bin",
    "id_bin": "1465",
    "list_language": [],
    "array_tags": [
      "digital",
      "date",
      "distance",
      "heartrate",
      "weather",
      "calories",
      "battery",
      "steps"
    ],
    "list_album": [
      {
        "id_album": "2433880",
        "link_thumb": "https://live.staticflickr.com/65535/51668717042_783718590c_o.gif",
        "title": "None"
      }
    ]
  },
  {
    "author": "LMB Studio",
    "link_thumb": "https://live.staticflickr.com/65535/51678351114_76385d2535_o.gif",
    "link_bin": "https://github.com/lmbstudiocontact/mb6_4/raw/main/SpiderManCartoon3_M6_2.bin",
    "id_bin": "SpiderManCartoon3_M6_2",
    "list_language": [
      {
        "author": "LMB Studio",
        "link_thumb": "https://live.staticflickr.com/65535/51677679486_be73c519e0_o.gif",
        "link_bin": "https://github.com/lmbstudiocontact/mb6_4/raw/main/SpiderManCartoon3_M6_2_English.bin",
        "name_language": "SpiderManCartoon3_M6_2_English",
        "id_bin_language": "SpiderManCartoon3_M6_2_English"
      },
      {
        "author": "LMB Studio",
        "link_thumb": "https://live.staticflickr.com/65535/51678559625_207cea3c9b_o.gif",
        "link_bin": "https://github.com/lmbstudiocontact/mb6_4/raw/main/SpiderManCartoon3_M6_2_Portuguese.bin",
        "name_language": "SpiderManCartoon3_M6_2_Portuguese",
        "id_bin_language": "SpiderManCartoon3_M6_2_Portuguese"
      },
      {
        "author": "LMB Studio",
        "link_thumb": "https://live.staticflickr.com/65535/51678351419_12c1951782_o.gif",
        "link_bin": "https://github.com/lmbstudiocontact/mb6_4/raw/main/SpiderManCartoon3_M6_2_Russian.bin",
        "name_language": "SpiderManCartoon3_M6_2_Russian",
        "id_bin_language": "SpiderManCartoon3_M6_2_Russian"
      },
      {
        "author": "LMB Studio",
        "link_thumb": "https://live.staticflickr.com/65535/51678351499_30be9beba1_o.gif",
        "link_bin": "https://github.com/lmbstudiocontact/mb6_4/raw/main/SpiderManCartoon3_M6_2_Spanish.bin",
        "name_language": "SpiderManCartoon3_M6_2_Spanish",
        "id_bin_language": "SpiderManCartoon3_M6_2_Spanish"
      }
    ],
    "array_tags": [],
    "list_album": [
      {
        "id_album": "890024494",
        "link_thumb": "https://live.staticflickr.com/65535/51678351114_76385d2535_o.gif",
        "title": "Spider Man Cartoon_M6_2"
      }
    ]
  },
  {
    "author": "LMB Studio",
    "link_thumb": "https://live.staticflickr.com/65535/51677681585_c58f2729fb_o.gif",
    "link_bin": "https://github.com/lmbstudiocontact/mb6_2/raw/main/FrozenCartoon9_M6_2.bin",
    "id_bin": "FrozenCartoon9_M6_2",
    "list_language": [
      {
        "author": "LMB Studio",
        "link_thumb": "https://live.staticflickr.com/65535/51677681840_8b04e0e50b_o.gif",
        "link_bin": "https://github.com/lmbstudiocontact/mb6_2/raw/main/FrozenCartoon9_M6_2_English.bin",
        "name_language": "FrozenCartoon9_M6_2_English",
        "id_bin_language": "FrozenCartoon9_M6_2_English"
      },
      {
        "author": "LMB Studio",
        "link_thumb": "https://live.staticflickr.com/65535/51677471774_be954e75ac_o.gif",
        "link_bin": "https://github.com/lmbstudiocontact/mb6_2/raw/main/FrozenCartoon9_M6_2_Portuguese.bin",
        "name_language": "FrozenCartoon9_M6_2_Portuguese",
        "id_bin_language": "FrozenCartoon9_M6_2_Portuguese"
      },
      {
        "author": "LMB Studio",
        "link_thumb": "https://live.staticflickr.com/65535/51676799941_dd8bf58239_o.gif",
        "link_bin": "https://github.com/lmbstudiocontact/mb6_2/raw/main/FrozenCartoon9_M6_2_Russian.bin",
        "name_language": "FrozenCartoon9_M6_2_Russian",
        "id_bin_language": "FrozenCartoon9_M6_2_Russian"
      },
      {
        "author": "LMB Studio",
        "link_thumb": "https://live.staticflickr.com/65535/51676800211_dc2fbb28a1_o.gif",
        "link_bin": "https://github.com/lmbstudiocontact/mb6_2/raw/main/FrozenCartoon9_M6_2_Spanish.bin",
        "name_language": "FrozenCartoon9_M6_2_Spanish",
        "id_bin_language": "FrozenCartoon9_M6_2_Spanish"
      }
    ],
    "array_tags": [],
    "list_album": [
      {
        "id_album": "-1319288147",
        "link_thumb": "https://live.staticflickr.com/65535/51677681585_c58f2729fb_o.gif",
        "title": "Frozen Cartoon_M6_2"
      }
    ]
  },
  {
    "author": "CTEPE0",
    "link_thumb": "https://live.staticflickr.com/65535/51669022927_9144408401_o.gif",
    "link_bin": "https://github.com/lmbstudiocontact/mb6_1/raw/main/981.bin",
    "id_bin": "981",
    "list_language": [],
    "array_tags": [
      "kat"
    ],
    "list_album": [
      {
        "id_album": "-2075887794",
        "link_thumb": "https://live.staticflickr.com/65535/51669022927_9144408401_o.gif",
        "title": "Cartoon"
      }
    ]
  },
  {
    "author": "LMB Studio",
    "link_thumb": "https://live.staticflickr.com/65535/51677109558_8b9a0b9cff_o.gif",
    "link_bin": "https://github.com/lmbstudiocontact/mb6_6/raw/main/HalloweenGhostWitch39_M6_2.bin",
    "id_bin": "HalloweenGhostWitch39_M6_2",
    "list_language": [
      {
        "author": "LMB Studio",
        "link_thumb": "https://live.staticflickr.com/65535/51676060232_604655616d_o.gif",
        "link_bin": "https://github.com/lmbstudiocontact/mb6_6/raw/main/HalloweenGhostWitch39_M6_2_English.bin",
        "name_language": "HalloweenGhostWitch39_M6_2_English",
        "id_bin_language": "HalloweenGhostWitch39_M6_2_English"
      },
      {
        "author": "LMB Studio",
        "link_thumb": "https://live.staticflickr.com/65535/51676863511_b81831cfe0_o.gif",
        "link_bin": "https://github.com/lmbstudiocontact/mb6_6/raw/main/HalloweenGhostWitch39_M6_2_Portuguese.bin",
        "name_language": "HalloweenGhostWitch39_M6_2_Portuguese",
        "id_bin_language": "HalloweenGhostWitch39_M6_2_Portuguese"
      },
      {
        "author": "LMB Studio",
        "link_thumb": "https://live.staticflickr.com/65535/51676060887_9b6b6f6af9_o.gif",
        "link_bin": "https://github.com/lmbstudiocontact/mb6_6/raw/main/HalloweenGhostWitch39_M6_2_Russian.bin",
        "name_language": "HalloweenGhostWitch39_M6_2_Russian",
        "id_bin_language": "HalloweenGhostWitch39_M6_2_Russian"
      },
      {
        "author": "LMB Studio",
        "link_thumb": "https://live.staticflickr.com/65535/51676864176_d301114442_o.gif",
        "link_bin": "https://github.com/lmbstudiocontact/mb6_6/raw/main/HalloweenGhostWitch39_M6_2_Spanish.bin",
        "name_language": "HalloweenGhostWitch39_M6_2_Spanish",
        "id_bin_language": "HalloweenGhostWitch39_M6_2_Spanish"
      }
    ],
    "array_tags": [],
    "list_album": [
      {
        "id_album": "-877220232",
        "link_thumb": "https://live.staticflickr.com/65535/51677109558_8b9a0b9cff_o.gif",
        "title": "Halloween Ghost Witch_M6_2"
      }
    ]
  },
  {
    "author": "LMB Studio",
    "link_thumb": "https://live.staticflickr.com/65535/51677490368_ba9a26e05e_o.gif",
    "link_bin": "https://github.com/lmbstudiocontact/mb6_3/raw/main/OnePieceAnime118_M6_2.bin",
    "id_bin": "OnePieceAnime118_M6_2",
    "list_language": [
      {
        "author": "LMB Studio",
        "link_thumb": "https://live.staticflickr.com/65535/51677915614_e5208e84a2_o.gif",
        "link_bin": "https://github.com/lmbstudiocontact/mb6_3/raw/main/OnePieceAnime118_M6_2_English.bin",
        "name_language": "OnePieceAnime118_M6_2_English",
        "id_bin_language": "OnePieceAnime118_M6_2_English"
      },
      {
        "author": "LMB Studio",
        "link_thumb": "https://live.staticflickr.com/65535/51677915789_a72560288d_o.gif",
        "link_bin": "https://github.com/lmbstudiocontact/mb6_3/raw/main/OnePieceAnime118_M6_2_Portuguese.bin",
        "name_language": "OnePieceAnime118_M6_2_Portuguese",
        "id_bin_language": "OnePieceAnime118_M6_2_Portuguese"
      },
      {
        "author": "LMB Studio",
        "link_thumb": "https://live.staticflickr.com/65535/51678124245_c9270def13_o.gif",
        "link_bin": "https://github.com/lmbstudiocontact/mb6_3/raw/main/OnePieceAnime118_M6_2_Russian.bin",
        "name_language": "OnePieceAnime118_M6_2_Russian",
        "id_bin_language": "OnePieceAnime118_M6_2_Russian"
      },
      {
        "author": "LMB Studio",
        "link_thumb": "https://live.staticflickr.com/65535/51677916309_746801cf58_o.gif",
        "link_bin": "https://github.com/lmbstudiocontact/mb6_3/raw/main/OnePieceAnime118_M6_2_Spanish.bin",
        "name_language": "OnePieceAnime118_M6_2_Spanish",
        "id_bin_language": "OnePieceAnime118_M6_2_Spanish"
      }
    ],
    "array_tags": [],
    "list_album": [
      {
        "id_album": "1669710643",
        "link_thumb": "https://live.staticflickr.com/65535/51677490368_ba9a26e05e_o.gif",
        "title": "One Piece Anime_M6_2"
      }
    ]
  },
  {
    "author": "csmarcelo1",
    "link_thumb": "https://live.staticflickr.com/65535/51669523971_8d1cc5c56c_o.gif",
    "link_bin": "https://github.com/lmbstudiocontact/mb6_0/raw/main/1552.bin",
    "id_bin": "1552",
    "list_language": [],
    "array_tags": [],
    "list_album": [
      {
        "id_album": "2433880",
        "link_thumb": "https://live.staticflickr.com/65535/51669523971_8d1cc5c56c_o.gif",
        "title": "None"
      }
    ]
  },
  {
    "author": "cvg8",
    "link_thumb": "https://live.staticflickr.com/65535/51669734141_26c2eac515_o.gif",
    "link_bin": "https://github.com/lmbstudiocontact/mb6_0/raw/main/56.bin",
    "id_bin": "56",
    "list_language": [],
    "array_tags": [
      "minimal",
      "simple"
    ],
    "list_album": [
      {
        "id_album": "2433880",
        "link_thumb": "https://live.staticflickr.com/65535/51669734141_26c2eac515_o.gif",
        "title": "None"
      }
    ]
  },
  {
    "author": "CTEPE0",
    "link_thumb": "https://live.staticflickr.com/65535/51669763621_8fdbb5f12d_o.gif",
    "link_bin": "https://github.com/lmbstudiocontact/mb6_0/raw/main/701.bin",
    "id_bin": "701",
    "list_language": [],
    "array_tags": [
      "cosmic"
    ],
    "list_album": [
      {
        "id_album": "2433880",
        "link_thumb": "https://live.staticflickr.com/65535/51669763621_8fdbb5f12d_o.gif",
        "title": "None"
      }
    ]
  },
  {
    "author": "LMB Studio",
    "link_thumb": "https://live.staticflickr.com/65535/51677845010_91e5fd8c33_o.gif",
    "link_bin": "https://github.com/lmbstudiocontact/mb6_6/raw/main/JokerHarleyQuinn23_M6_2.bin",
    "id_bin": "JokerHarleyQuinn23_M6_2",
    "list_language": [
      {
        "author": "LMB Studio",
        "link_thumb": "https://live.staticflickr.com/65535/51676963176_3513324a0f_o.gif",
        "link_bin": "https://github.com/lmbstudiocontact/mb6_6/raw/main/JokerHarleyQuinn23_M6_2_English.bin",
        "name_language": "JokerHarleyQuinn23_M6_2_English",
        "id_bin_language": "JokerHarleyQuinn23_M6_2_English"
      },
      {
        "author": "LMB Studio",
        "link_thumb": "https://live.staticflickr.com/65535/51676160057_5551ca473f_o.gif",
        "link_bin": "https://github.com/lmbstudiocontact/mb6_6/raw/main/JokerHarleyQuinn23_M6_2_Portuguese.bin",
        "name_language": "JokerHarleyQuinn23_M6_2_Portuguese",
        "id_bin_language": "JokerHarleyQuinn23_M6_2_Portuguese"
      },
      {
        "author": "LMB Studio",
        "link_thumb": "https://live.staticflickr.com/65535/51677210098_30cf7858eb_o.gif",
        "link_bin": "https://github.com/lmbstudiocontact/mb6_6/raw/main/JokerHarleyQuinn23_M6_2_Russian.bin",
        "name_language": "JokerHarleyQuinn23_M6_2_Russian",
        "id_bin_language": "JokerHarleyQuinn23_M6_2_Russian"
      },
      {
        "author": "LMB Studio",
        "link_thumb": "https://live.staticflickr.com/65535/51677210363_2cfb122906_o.gif",
        "link_bin": "https://github.com/lmbstudiocontact/mb6_6/raw/main/JokerHarleyQuinn23_M6_2_Spanish.bin",
        "name_language": "JokerHarleyQuinn23_M6_2_Spanish",
        "id_bin_language": "JokerHarleyQuinn23_M6_2_Spanish"
      }
    ],
    "array_tags": [],
    "list_album": [
      {
        "id_album": "-1985531774",
        "link_thumb": "https://live.staticflickr.com/65535/51677845010_91e5fd8c33_o.gif",
        "title": "Joker Harley Quinn_M6_2"
      }
    ]
  },
  {
    "author": "ZanarkTempest",
    "link_thumb": "https://live.staticflickr.com/65535/51668833677_331910975f_o.gif",
    "link_bin": "https://github.com/lmbstudiocontact/mb6_1/raw/main/2262.bin",
    "id_bin": "2262",
    "list_language": [],
    "array_tags": [
      "marvel",
      "heartrate",
      "games",
      "serie",
      "steps"
    ],
    "list_album": [
      {
        "id_album": "-2075887794",
        "link_thumb": "https://live.staticflickr.com/65535/51668833677_331910975f_o.gif",
        "title": "Cartoon"
      }
    ]
  },
  {
    "author": "pep0jr",
    "link_thumb": "https://live.staticflickr.com/65535/51670372170_9719dc9f5a_o.gif",
    "link_bin": "https://github.com/lmbstudiocontact/mb6_0/raw/main/1297.bin",
    "id_bin": "1297",
    "list_language": [],
    "array_tags": [
      "anime"
    ],
    "list_album": [
      {
        "id_album": "63410260",
        "link_thumb": "https://live.staticflickr.com/65535/51670372170_9719dc9f5a_o.gif",
        "title": "Anime"
      }
    ]
  },
  {
    "author": "LMB Studio",
    "link_thumb": "https://live.staticflickr.com/65535/51677885638_c551647cfa_o.gif",
    "link_bin": "https://github.com/lmbstudiocontact/mb6_4/raw/main/Shiv13_M6_2.bin",
    "id_bin": "Shiv13_M6_2",
    "list_language": [
      {
        "author": "LMB Studio",
        "link_thumb": "https://live.staticflickr.com/65535/51678516570_467ed001d9_o.gif",
        "link_bin": "https://github.com/lmbstudiocontact/mb6_4/raw/main/Shiv13_M6_2_English.bin",
        "name_language": "Shiv13_M6_2_English",
        "id_bin_language": "Shiv13_M6_2_English"
      },
      {
        "author": "LMB Studio",
        "link_thumb": "https://live.staticflickr.com/65535/51677886118_2edf0053a4_o.gif",
        "link_bin": "https://github.com/lmbstudiocontact/mb6_4/raw/main/Shiv13_M6_2_Portuguese.bin",
        "name_language": "Shiv13_M6_2_Portuguese",
        "id_bin_language": "Shiv13_M6_2_Portuguese"
      },
      {
        "author": "LMB Studio",
        "link_thumb": "https://live.staticflickr.com/65535/51676830167_c5921dd1eb_o.gif",
        "link_bin": "https://github.com/lmbstudiocontact/mb6_4/raw/main/Shiv13_M6_2_Russian.bin",
        "name_language": "Shiv13_M6_2_Russian",
        "id_bin_language": "Shiv13_M6_2_Russian"
      },
      {
        "author": "LMB Studio",
        "link_thumb": "https://live.staticflickr.com/65535/51678517140_3e93991736_o.gif",
        "link_bin": "https://github.com/lmbstudiocontact/mb6_4/raw/main/Shiv13_M6_2_Spanish.bin",
        "name_language": "Shiv13_M6_2_Spanish",
        "id_bin_language": "Shiv13_M6_2_Spanish"
      }
    ],
    "array_tags": [],
    "list_album": [
      {
        "id_album": "-959254855",
        "link_thumb": "https://live.staticflickr.com/65535/51677885638_c551647cfa_o.gif",
        "title": "Shiv_M6_2"
      }
    ]
  },
  {
    "author": "LMB Studio",
    "link_thumb": "https://live.staticflickr.com/65535/51677580293_46afc057c6_o.gif",
    "link_bin": "https://github.com/lmbstudiocontact/mb6_3/raw/main/OnePieceAnime70_M6_2.bin",
    "id_bin": "OnePieceAnime70_M6_2",
    "list_language": [
      {
        "author": "LMB Studio",
        "link_thumb": "https://live.staticflickr.com/65535/51677332766_27c9e0f583_o.gif",
        "link_bin": "https://github.com/lmbstudiocontact/mb6_3/raw/main/OnePieceAnime70_M6_2_English.bin",
        "name_language": "OnePieceAnime70_M6_2_English",
        "id_bin_language": "OnePieceAnime70_M6_2_English"
      },
      {
        "author": "LMB Studio",
        "link_thumb": "https://live.staticflickr.com/65535/51678004719_1fa0ef9140_o.gif",
        "link_bin": "https://github.com/lmbstudiocontact/mb6_3/raw/main/OnePieceAnime70_M6_2_Portuguese.bin",
        "name_language": "OnePieceAnime70_M6_2_Portuguese",
        "id_bin_language": "OnePieceAnime70_M6_2_Portuguese"
      },
      {
        "author": "LMB Studio",
        "link_thumb": "https://live.staticflickr.com/65535/51677333251_02375369ab_o.gif",
        "link_bin": "https://github.com/lmbstudiocontact/mb6_3/raw/main/OnePieceAnime70_M6_2_Russian.bin",
        "name_language": "OnePieceAnime70_M6_2_Russian",
        "id_bin_language": "OnePieceAnime70_M6_2_Russian"
      },
      {
        "author": "LMB Studio",
        "link_thumb": "https://live.staticflickr.com/65535/51678005199_9767b323c6_o.gif",
        "link_bin": "https://github.com/lmbstudiocontact/mb6_3/raw/main/OnePieceAnime70_M6_2_Spanish.bin",
        "name_language": "OnePieceAnime70_M6_2_Spanish",
        "id_bin_language": "OnePieceAnime70_M6_2_Spanish"
      }
    ],
    "array_tags": [],
    "list_album": [
      {
        "id_album": "1669710643",
        "link_thumb": "https://live.staticflickr.com/65535/51677580293_46afc057c6_o.gif",
        "title": "One Piece Anime_M6_2"
      }
    ]
  },
  {
    "author": "LMB Studio",
    "link_thumb": "https://live.staticflickr.com/65535/51675976162_dba3cf0252_o.gif",
    "link_bin": "https://github.com/lmbstudiocontact/mb6_2/raw/main/FoxArt0_M6_2.bin",
    "id_bin": "FoxArt0_M6_2",
    "list_language": [
      {
        "author": "LMB Studio",
        "link_thumb": "https://live.staticflickr.com/65535/51677451679_066d8ec1b5_o.gif",
        "link_bin": "https://github.com/lmbstudiocontact/mb6_2/raw/main/FoxArt0_M6_2_English.bin",
        "name_language": "FoxArt0_M6_2_English",
        "id_bin_language": "FoxArt0_M6_2_English"
      },
      {
        "author": "LMB Studio",
        "link_thumb": "https://live.staticflickr.com/65535/51675976672_bb2eca7806_o.gif",
        "link_bin": "https://github.com/lmbstudiocontact/mb6_2/raw/main/FoxArt0_M6_2_Portuguese.bin",
        "name_language": "FoxArt0_M6_2_Portuguese",
        "id_bin_language": "FoxArt0_M6_2_Portuguese"
      },
      {
        "author": "LMB Studio",
        "link_thumb": "https://live.staticflickr.com/65535/51676780401_9997037898_o.gif",
        "link_bin": "https://github.com/lmbstudiocontact/mb6_2/raw/main/FoxArt0_M6_2_Russian.bin",
        "name_language": "FoxArt0_M6_2_Russian",
        "id_bin_language": "FoxArt0_M6_2_Russian"
      },
      {
        "author": "LMB Studio",
        "link_thumb": "https://live.staticflickr.com/65535/51677027443_99cabb97e0_o.gif",
        "link_bin": "https://github.com/lmbstudiocontact/mb6_2/raw/main/FoxArt0_M6_2_Spanish.bin",
        "name_language": "FoxArt0_M6_2_Spanish",
        "id_bin_language": "FoxArt0_M6_2_Spanish"
      }
    ],
    "array_tags": [],
    "list_album": [
      {
        "id_album": "1857757129",
        "link_thumb": "https://live.staticflickr.com/65535/51675976162_dba3cf0252_o.gif",
        "title": "Fox Art_M6_2"
      }
    ]
  },
  {
    "author": "mediatouch",
    "link_thumb": "https://live.staticflickr.com/65535/51669730983_d3ff101d3e_o.gif",
    "link_bin": "https://github.com/lmbstudiocontact/mb6_0/raw/main/1279.bin",
    "id_bin": "1279",
    "list_language": [],
    "array_tags": [
      "digital",
      "date",
      "battery",
      "day",
      "status"
    ],
    "list_album": [
      {
        "id_album": "2433880",
        "link_thumb": "https://live.staticflickr.com/65535/51669730983_d3ff101d3e_o.gif",
        "title": "None"
      }
    ]
  },
  {
    "author": "ZanarkTempest",
    "link_thumb": "https://live.staticflickr.com/65535/51669559841_b734d3e5b9_o.gif",
    "link_bin": "https://github.com/lmbstudiocontact/mb6_1/raw/main/1798.bin",
    "id_bin": "1798",
    "list_language": [],
    "array_tags": [
      "dragonball",
      "anime"
    ],
    "list_album": [
      {
        "id_album": "63410260",
        "link_thumb": "https://live.staticflickr.com/65535/51669559841_b734d3e5b9_o.gif",
        "title": "Anime"
      }
    ]
  },
  {
    "author": "Rosta949",
    "link_thumb": "https://live.staticflickr.com/65535/51670521935_44c881f5c4_o.gif",
    "link_bin": "https://github.com/lmbstudiocontact/mb6_1/raw/main/2314.bin",
    "id_bin": "2314",
    "list_language": [],
    "array_tags": [
      "date",
      "distance",
      "weekday",
      "calories",
      "battery",
      "steps",
      "analog",
      "weather",
      "pulse",
      "pai",
      "time",
      "status"
    ],
    "list_album": [
      {
        "id_album": "2433880",
        "link_thumb": "https://live.staticflickr.com/65535/51670521935_44c881f5c4_o.gif",
        "title": "None"
      }
    ]
  },
  {
    "author": "Rosta949",
    "link_thumb": "https://live.staticflickr.com/65535/51670424245_f84a59dc62_o.gif",
    "link_bin": "https://github.com/lmbstudiocontact/mb6_1/raw/main/1730.bin",
    "id_bin": "1730",
    "list_language": [],
    "array_tags": [
      "date",
      "weekday",
      "battery",
      "animation"
    ],
    "list_album": [
      {
        "id_album": "-2075887794",
        "link_thumb": "https://live.staticflickr.com/65535/51670424245_f84a59dc62_o.gif",
        "title": "Cartoon"
      }
    ]
  },
  {
    "author": "ZanarkTempest",
    "link_thumb": "https://live.staticflickr.com/65535/51669816308_0b00419d97_o.gif",
    "link_bin": "https://github.com/lmbstudiocontact/mb6_1/raw/main/1881.bin",
    "id_bin": "1881",
    "list_language": [],
    "array_tags": [
      "marvel"
    ],
    "list_album": [
      {
        "id_album": "-2075887794",
        "link_thumb": "https://live.staticflickr.com/65535/51669816308_0b00419d97_o.gif",
        "title": "Cartoon"
      }
    ]
  },
  {
    "author": "cvg8",
    "link_thumb": "https://live.staticflickr.com/65535/51670410184_880002b49a_o.gif",
    "link_bin": "https://github.com/lmbstudiocontact/mb6_0/raw/main/51.bin",
    "id_bin": "51",
    "list_language": [],
    "array_tags": [],
    "list_album": [
      {
        "id_album": "2433880",
        "link_thumb": "https://live.staticflickr.com/65535/51670410184_880002b49a_o.gif",
        "title": "None"
      }
    ]
  },
  {
    "author": "ZanarkTempest",
    "link_thumb": "https://live.staticflickr.com/65535/51669874213_39b639e2ba_o.gif",
    "link_bin": "https://github.com/lmbstudiocontact/mb6_1/raw/main/2270.bin",
    "id_bin": "2270",
    "list_language": [],
    "array_tags": [
      "heartrate",
      "steps",
      "anime"
    ],
    "list_album": [
      {
        "id_album": "63410260",
        "link_thumb": "https://live.staticflickr.com/65535/51669874213_39b639e2ba_o.gif",
        "title": "Anime"
      }
    ]
  },
  {
    "author": "nortx",
    "link_thumb": "https://live.staticflickr.com/65535/51668932127_d4ac0fa160_o.gif",
    "link_bin": "https://github.com/lmbstudiocontact/mb6_0/raw/main/532.bin",
    "id_bin": "532",
    "list_language": [],
    "array_tags": [],
    "list_album": [
      {
        "id_album": "2433880",
        "link_thumb": "https://live.staticflickr.com/65535/51668932127_d4ac0fa160_o.gif",
        "title": "None"
      }
    ]
  },
  {
    "author": "mpsspencer",
    "link_thumb": "https://live.staticflickr.com/65535/51669019472_07f54bf963_o.gif",
    "link_bin": "https://github.com/lmbstudiocontact/mb6_1/raw/main/964.bin",
    "id_bin": "964",
    "list_language": [],
    "array_tags": [
      "date",
      "marvel",
      "bluetooth",
      "notdisturb",
      "alarm",
      "pai",
      "lock",
      "time",
      "battery"
    ],
    "list_album": [
      {
        "id_album": "74534672",
        "link_thumb": "https://live.staticflickr.com/65535/51669019472_07f54bf963_o.gif",
        "title": "Movie"
      }
    ]
  },
  {
    "author": "LMB Studio",
    "link_thumb": "https://live.staticflickr.com/65535/51677031263_959dc4d9a5_o.gif",
    "link_bin": "https://github.com/lmbstudiocontact/mb6_2/raw/main/FoxArt4_M6_2.bin",
    "id_bin": "FoxArt4_M6_2",
    "list_language": [
      {
        "author": "LMB Studio",
        "link_thumb": "https://live.staticflickr.com/65535/51675980872_5cc8793bb5_o.gif",
        "link_bin": "https://github.com/lmbstudiocontact/mb6_2/raw/main/FoxArt4_M6_2_English.bin",
        "name_language": "FoxArt4_M6_2_English",
        "id_bin_language": "FoxArt4_M6_2_English"
      },
      {
        "author": "LMB Studio",
        "link_thumb": "https://live.staticflickr.com/65535/51677456459_7e4a9db7c6_o.gif",
        "link_bin": "https://github.com/lmbstudiocontact/mb6_2/raw/main/FoxArt4_M6_2_Portuguese.bin",
        "name_language": "FoxArt4_M6_2_Portuguese",
        "id_bin_language": "FoxArt4_M6_2_Portuguese"
      },
      {
        "author": "LMB Studio",
        "link_thumb": "https://live.staticflickr.com/65535/51677456649_52bca0ff02_o.gif",
        "link_bin": "https://github.com/lmbstudiocontact/mb6_2/raw/main/FoxArt4_M6_2_Russian.bin",
        "name_language": "FoxArt4_M6_2_Russian",
        "id_bin_language": "FoxArt4_M6_2_Russian"
      },
      {
        "author": "LMB Studio",
        "link_thumb": "https://live.staticflickr.com/65535/51677941818_41b8e1c05a_o.gif",
        "link_bin": "https://github.com/lmbstudiocontact/mb6_2/raw/main/FoxArt4_M6_2_Spanish.bin",
        "name_language": "FoxArt4_M6_2_Spanish",
        "id_bin_language": "FoxArt4_M6_2_Spanish"
      }
    ],
    "array_tags": [],
    "list_album": [
      {
        "id_album": "1857757129",
        "link_thumb": "https://live.staticflickr.com/65535/51677031263_959dc4d9a5_o.gif",
        "title": "Fox Art_M6_2"
      }
    ]
  },
  {
    "author": "LMB Studio",
    "link_thumb": "https://live.staticflickr.com/65535/51677423265_ae5e3f7c61_o.gif",
    "link_bin": "https://github.com/lmbstudiocontact/mb6_5/raw/main/DisneyCartoon15_M6_2.bin",
    "id_bin": "DisneyCartoon15_M6_2",
    "list_language": [
      {
        "author": "LMB Studio",
        "link_thumb": "https://live.staticflickr.com/65535/51676543956_ab06c3a64d_o.gif",
        "link_bin": "https://github.com/lmbstudiocontact/mb6_5/raw/main/DisneyCartoon15_M6_2_English.bin",
        "name_language": "DisneyCartoon15_M6_2_English",
        "id_bin_language": "DisneyCartoon15_M6_2_English"
      },
      {
        "author": "LMB Studio",
        "link_thumb": "https://live.staticflickr.com/65535/51675740547_7765cddf1e_o.gif",
        "link_bin": "https://github.com/lmbstudiocontact/mb6_5/raw/main/DisneyCartoon15_M6_2_Portuguese.bin",
        "name_language": "DisneyCartoon15_M6_2_Portuguese",
        "id_bin_language": "DisneyCartoon15_M6_2_Portuguese"
      },
      {
        "author": "LMB Studio",
        "link_thumb": "https://live.staticflickr.com/65535/51677692691_03cced1a68_o.gif",
        "link_bin": "https://github.com/lmbstudiocontact/mb6_5/raw/main/DisneyCartoon15_M6_2_Russian.bin",
        "name_language": "DisneyCartoon15_M6_2_Russian",
        "id_bin_language": "DisneyCartoon15_M6_2_Russian"
      },
      {
        "author": "LMB Studio",
        "link_thumb": "https://live.staticflickr.com/65535/51676544321_1ae6330b77_o.gif",
        "link_bin": "https://github.com/lmbstudiocontact/mb6_5/raw/main/DisneyCartoon15_M6_2_Spanish.bin",
        "name_language": "DisneyCartoon15_M6_2_Spanish",
        "id_bin_language": "DisneyCartoon15_M6_2_Spanish"
      }
    ],
    "array_tags": [],
    "list_album": [
      {
        "id_album": "-1858058375",
        "link_thumb": "https://live.staticflickr.com/65535/51677423265_ae5e3f7c61_o.gif",
        "title": "Disney Cartoon_M6_2"
      }
    ]
  },
  {
    "author": "LMB Studio",
    "link_thumb": "https://live.staticflickr.com/65535/51677079766_b7c241e49d_o.gif",
    "link_bin": "https://github.com/lmbstudiocontact/mb6_7/raw/main/Lilo\u0026StitchCartoon24_M6_2.bin",
    "id_bin": "Lilo\u0026StitchCartoon24_M6_2",
    "list_language": [
      {
        "author": "LMB Studio",
        "link_thumb": "https://live.staticflickr.com/65535/51676275447_a8cb8562e7_o.gif",
        "link_bin": "https://github.com/lmbstudiocontact/mb6_7/raw/main/Lilo\u0026StitchCartoon24_M6_2_English.bin",
        "name_language": "Lilo\u0026StitchCartoon24_M6_2_English",
        "id_bin_language": "Lilo\u0026StitchCartoon24_M6_2_English"
      },
      {
        "author": "LMB Studio",
        "link_thumb": "https://live.staticflickr.com/65535/51676275727_a681b1bab3_o.gif",
        "link_bin": "https://github.com/lmbstudiocontact/mb6_7/raw/main/Lilo\u0026StitchCartoon24_M6_2_Portuguese.bin",
        "name_language": "Lilo\u0026StitchCartoon24_M6_2_Portuguese",
        "id_bin_language": "Lilo\u0026StitchCartoon24_M6_2_Portuguese"
      },
      {
        "author": "LMB Studio",
        "link_thumb": "https://live.staticflickr.com/65535/51677327893_10125d8d0a_o.gif",
        "link_bin": "https://github.com/lmbstudiocontact/mb6_7/raw/main/Lilo\u0026StitchCartoon24_M6_2_Russian.bin",
        "name_language": "Lilo\u0026StitchCartoon24_M6_2_Russian",
        "id_bin_language": "Lilo\u0026StitchCartoon24_M6_2_Russian"
      },
      {
        "author": "LMB Studio",
        "link_thumb": "https://live.staticflickr.com/65535/51677962540_f4dd2f8d62_o.gif",
        "link_bin": "https://github.com/lmbstudiocontact/mb6_7/raw/main/Lilo\u0026StitchCartoon24_M6_2_Spanish.bin",
        "name_language": "Lilo\u0026StitchCartoon24_M6_2_Spanish",
        "id_bin_language": "Lilo\u0026StitchCartoon24_M6_2_Spanish"
      }
    ],
    "array_tags": [],
    "list_album": [
      {
        "id_album": "1677497602",
        "link_thumb": "https://live.staticflickr.com/65535/51677079766_b7c241e49d_o.gif",
        "title": "Lilo \u0026 Stitch Cartoon_M6_2"
      }
    ]
  },
  {
    "author": "NEORUAA",
    "link_thumb": "https://live.staticflickr.com/65535/51670428484_b569f44fde_o.gif",
    "link_bin": "https://github.com/lmbstudiocontact/mb6_0/raw/main/6.bin",
    "id_bin": "6",
    "list_language": [],
    "array_tags": [
      "digital",
      "date"
    ],
    "list_album": [
      {
        "id_album": "2433880",
        "link_thumb": "https://live.staticflickr.com/65535/51670428484_b569f44fde_o.gif",
        "title": "None"
      }
    ]
  },
  {
    "author": "ZanarkTempest",
    "link_thumb": "https://live.staticflickr.com/65535/51670246239_be3e66cfaf_o.gif",
    "link_bin": "https://github.com/lmbstudiocontact/mb6_1/raw/main/1793.bin",
    "id_bin": "1793",
    "list_language": [],
    "array_tags": [
      "anime"
    ],
    "list_album": [
      {
        "id_album": "63410260",
        "link_thumb": "https://live.staticflickr.com/65535/51670246239_be3e66cfaf_o.gif",
        "title": "Anime"
      }
    ]
  },
  {
    "author": "LMB Studio",
    "link_thumb": "https://live.staticflickr.com/65535/51677151343_7491109058_o.gif",
    "link_bin": "https://github.com/lmbstudiocontact/mb6_6/raw/main/HorrorArt22_M6_2.bin",
    "id_bin": "HorrorArt22_M6_2",
    "list_language": [
      {
        "author": "LMB Studio",
        "link_thumb": "https://live.staticflickr.com/65535/51677577944_c98c3f1852_o.gif",
        "link_bin": "https://github.com/lmbstudiocontact/mb6_6/raw/main/HorrorArt22_M6_2_English.bin",
        "name_language": "HorrorArt22_M6_2_English",
        "id_bin_language": "HorrorArt22_M6_2_English"
      },
      {
        "author": "LMB Studio",
        "link_thumb": "https://live.staticflickr.com/65535/51677578264_b289f8458d_o.gif",
        "link_bin": "https://github.com/lmbstudiocontact/mb6_6/raw/main/HorrorArt22_M6_2_Portuguese.bin",
        "name_language": "HorrorArt22_M6_2_Portuguese",
        "id_bin_language": "HorrorArt22_M6_2_Portuguese"
      },
      {
        "author": "LMB Studio",
        "link_thumb": "https://live.staticflickr.com/65535/51677578479_f92bfc65ac_o.gif",
        "link_bin": "https://github.com/lmbstudiocontact/mb6_6/raw/main/HorrorArt22_M6_2_Russian.bin",
        "name_language": "HorrorArt22_M6_2_Russian",
        "id_bin_language": "HorrorArt22_M6_2_Russian"
      },
      {
        "author": "LMB Studio",
        "link_thumb": "https://live.staticflickr.com/65535/51676905551_94b1bacb53_o.gif",
        "link_bin": "https://github.com/lmbstudiocontact/mb6_6/raw/main/HorrorArt22_M6_2_Spanish.bin",
        "name_language": "HorrorArt22_M6_2_Spanish",
        "id_bin_language": "HorrorArt22_M6_2_Spanish"
      }
    ],
    "array_tags": [],
    "list_album": [
      {
        "id_album": "1925454094",
        "link_thumb": "https://live.staticflickr.com/65535/51677151343_7491109058_o.gif",
        "title": "Horror Art_M6_2"
      }
    ]
  },
  {
    "author": "ZanarkTempest",
    "link_thumb": "https://live.staticflickr.com/65535/51670255709_40ed5d31a2_o.gif",
    "link_bin": "https://github.com/lmbstudiocontact/mb6_1/raw/main/1835.bin",
    "id_bin": "1835",
    "list_language": [],
    "array_tags": [
      "anime"
    ],
    "list_album": [
      {
        "id_album": "63410260",
        "link_thumb": "https://live.staticflickr.com/65535/51670255709_40ed5d31a2_o.gif",
        "title": "Anime"
      }
    ]
  },
  {
    "author": "LMB Studio",
    "link_thumb": "https://live.staticflickr.com/65535/51677680485_dcf88ccfcb_o.gif",
    "link_bin": "https://github.com/lmbstudiocontact/mb6_2/raw/main/FrozenCartoon8_M6_2.bin",
    "id_bin": "FrozenCartoon8_M6_2",
    "list_language": [
      {
        "author": "LMB Studio",
        "link_thumb": "https://live.staticflickr.com/65535/51677045533_2ff0cf42ee_o.gif",
        "link_bin": "https://github.com/lmbstudiocontact/mb6_2/raw/main/FrozenCartoon8_M6_2_English.bin",
        "name_language": "FrozenCartoon8_M6_2_English",
        "id_bin_language": "FrozenCartoon8_M6_2_English"
      },
      {
        "author": "LMB Studio",
        "link_thumb": "https://live.staticflickr.com/65535/51677045833_ef6be84d4c_o.gif",
        "link_bin": "https://github.com/lmbstudiocontact/mb6_2/raw/main/FrozenCartoon8_M6_2_Portuguese.bin",
        "name_language": "FrozenCartoon8_M6_2_Portuguese",
        "id_bin_language": "FrozenCartoon8_M6_2_Portuguese"
      },
      {
        "author": "LMB Studio",
        "link_thumb": "https://live.staticflickr.com/65535/51675995962_8e60d68342_o.gif",
        "link_bin": "https://github.com/lmbstudiocontact/mb6_2/raw/main/FrozenCartoon8_M6_2_Russian.bin",
        "name_language": "FrozenCartoon8_M6_2_Russian",
        "id_bin_language": "FrozenCartoon8_M6_2_Russian"
      },
      {
        "author": "LMB Studio",
        "link_thumb": "https://live.staticflickr.com/65535/51677681425_842c6f7bb6_o.gif",
        "link_bin": "https://github.com/lmbstudiocontact/mb6_2/raw/main/FrozenCartoon8_M6_2_Spanish.bin",
        "name_language": "FrozenCartoon8_M6_2_Spanish",
        "id_bin_language": "FrozenCartoon8_M6_2_Spanish"
      }
    ],
    "array_tags": [],
    "list_album": [
      {
        "id_album": "-1319288147",
        "link_thumb": "https://live.staticflickr.com/65535/51677680485_dcf88ccfcb_o.gif",
        "title": "Frozen Cartoon_M6_2"
      }
    ]
  },
  {
    "author": "LMB Studio",
    "link_thumb": "https://live.staticflickr.com/65535/51676798288_22eaa169ae_o.gif",
    "link_bin": "https://github.com/lmbstudiocontact/mb6_5/raw/main/DisneyCartoon22_M6_2.bin",
    "id_bin": "DisneyCartoon22_M6_2",
    "list_language": [
      {
        "author": "LMB Studio",
        "link_thumb": "https://live.staticflickr.com/65535/51676798623_585f107710_o.gif",
        "link_bin": "https://github.com/lmbstudiocontact/mb6_5/raw/main/DisneyCartoon22_M6_2_English.bin",
        "name_language": "DisneyCartoon22_M6_2_English",
        "id_bin_language": "DisneyCartoon22_M6_2_English"
      },
      {
        "author": "LMB Studio",
        "link_thumb": "https://live.staticflickr.com/65535/51677225744_17140aa97f_o.gif",
        "link_bin": "https://github.com/lmbstudiocontact/mb6_5/raw/main/DisneyCartoon22_M6_2_Portuguese.bin",
        "name_language": "DisneyCartoon22_M6_2_Portuguese",
        "id_bin_language": "DisneyCartoon22_M6_2_Portuguese"
      },
      {
        "author": "LMB Studio",
        "link_thumb": "https://live.staticflickr.com/65535/51675749722_b033be75ff_o.gif",
        "link_bin": "https://github.com/lmbstudiocontact/mb6_5/raw/main/DisneyCartoon22_M6_2_Russian.bin",
        "name_language": "DisneyCartoon22_M6_2_Russian",
        "id_bin_language": "DisneyCartoon22_M6_2_Russian"
      },
      {
        "author": "LMB Studio",
        "link_thumb": "https://live.staticflickr.com/65535/51675750062_58ce3ee26a_o.gif",
        "link_bin": "https://github.com/lmbstudiocontact/mb6_5/raw/main/DisneyCartoon22_M6_2_Spanish.bin",
        "name_language": "DisneyCartoon22_M6_2_Spanish",
        "id_bin_language": "DisneyCartoon22_M6_2_Spanish"
      }
    ],
    "array_tags": [],
    "list_album": [
      {
        "id_album": "-1858058375",
        "link_thumb": "https://live.staticflickr.com/65535/51676798288_22eaa169ae_o.gif",
        "title": "Disney Cartoon_M6_2"
      }
    ]
  },
  {
    "author": "LMB Studio",
    "link_thumb": "https://live.staticflickr.com/65535/51677111163_5cccd371a3_o.gif",
    "link_bin": "https://github.com/lmbstudiocontact/mb6_6/raw/main/HalloweenGhostWitch3_M6_2.bin",
    "id_bin": "HalloweenGhostWitch3_M6_2",
    "list_language": [
      {
        "author": "LMB Studio",
        "link_thumb": "https://live.staticflickr.com/65535/51676061777_cd50dfc6f0_o.gif",
        "link_bin": "https://github.com/lmbstudiocontact/mb6_6/raw/main/HalloweenGhostWitch3_M6_2_English.bin",
        "name_language": "HalloweenGhostWitch3_M6_2_English",
        "id_bin_language": "HalloweenGhostWitch3_M6_2_English"
      },
      {
        "author": "LMB Studio",
        "link_thumb": "https://live.staticflickr.com/65535/51677746820_16dd48caec_o.gif",
        "link_bin": "https://github.com/lmbstudiocontact/mb6_6/raw/main/HalloweenGhostWitch3_M6_2_Portuguese.bin",
        "name_language": "HalloweenGhostWitch3_M6_2_Portuguese",
        "id_bin_language": "HalloweenGhostWitch3_M6_2_Portuguese"
      },
      {
        "author": "LMB Studio",
        "link_thumb": "https://live.staticflickr.com/65535/51677537529_701af5c2e2_o.gif",
        "link_bin": "https://github.com/lmbstudiocontact/mb6_6/raw/main/HalloweenGhostWitch3_M6_2_Russian.bin",
        "name_language": "HalloweenGhostWitch3_M6_2_Russian",
        "id_bin_language": "HalloweenGhostWitch3_M6_2_Russian"
      },
      {
        "author": "LMB Studio",
        "link_thumb": "https://live.staticflickr.com/65535/51677747235_6f8d0a1255_o.gif",
        "link_bin": "https://github.com/lmbstudiocontact/mb6_6/raw/main/HalloweenGhostWitch3_M6_2_Spanish.bin",
        "name_language": "HalloweenGhostWitch3_M6_2_Spanish",
        "id_bin_language": "HalloweenGhostWitch3_M6_2_Spanish"
      }
    ],
    "array_tags": [],
    "list_album": [
      {
        "id_album": "-877220232",
        "link_thumb": "https://live.staticflickr.com/65535/51677111163_5cccd371a3_o.gif",
        "title": "Halloween Ghost Witch_M6_2"
      }
    ]
  },
  {
    "author": "LMB Studio",
    "link_thumb": "https://live.staticflickr.com/65535/51676816037_616d7611ff_o.gif",
    "link_bin": "https://github.com/lmbstudiocontact/mb6_4/raw/main/SevendeadlysinsAnime36_M6_2.bin",
    "id_bin": "SevendeadlysinsAnime36_M6_2",
    "list_language": [
      {
        "author": "LMB Studio",
        "link_thumb": "https://live.staticflickr.com/65535/51678503170_0d7f833bba_o.gif",
        "link_bin": "https://github.com/lmbstudiocontact/mb6_4/raw/main/SevendeadlysinsAnime36_M6_2_English.bin",
        "name_language": "SevendeadlysinsAnime36_M6_2_English",
        "id_bin_language": "SevendeadlysinsAnime36_M6_2_English"
      },
      {
        "author": "LMB Studio",
        "link_thumb": "https://live.staticflickr.com/65535/51676816532_48c5ab1eb0_o.gif",
        "link_bin": "https://github.com/lmbstudiocontact/mb6_4/raw/main/SevendeadlysinsAnime36_M6_2_Portuguese.bin",
        "name_language": "SevendeadlysinsAnime36_M6_2_Portuguese",
        "id_bin_language": "SevendeadlysinsAnime36_M6_2_Portuguese"
      },
      {
        "author": "LMB Studio",
        "link_thumb": "https://live.staticflickr.com/65535/51678503535_6f99ef24f4_o.gif",
        "link_bin": "https://github.com/lmbstudiocontact/mb6_4/raw/main/SevendeadlysinsAnime36_M6_2_Russian.bin",
        "name_language": "SevendeadlysinsAnime36_M6_2_Russian",
        "id_bin_language": "SevendeadlysinsAnime36_M6_2_Russian"
      },
      {
        "author": "LMB Studio",
        "link_thumb": "https://live.staticflickr.com/65535/51678503730_70843e3d8d_o.gif",
        "link_bin": "https://github.com/lmbstudiocontact/mb6_4/raw/main/SevendeadlysinsAnime36_M6_2_Spanish.bin",
        "name_language": "SevendeadlysinsAnime36_M6_2_Spanish",
        "id_bin_language": "SevendeadlysinsAnime36_M6_2_Spanish"
      }
    ],
    "array_tags": [],
    "list_album": [
      {
        "id_album": "1052927760",
        "link_thumb": "https://live.staticflickr.com/65535/51676816037_616d7611ff_o.gif",
        "title": "Seven deadly sins Anime_M6_2"
      }
    ]
  },
  {
    "author": "None",
    "link_thumb": "https://live.staticflickr.com/65535/51670630320_226eb221b3_o.gif",
    "link_bin": "https://github.com/lmbstudiocontact/mb6_0/raw/main/646.bin",
    "id_bin": "646",
    "list_language": [],
    "array_tags": [
      "digital",
      "date",
      "heartrate",
      "calories",
      "battery",
      "steps"
    ],
    "list_album": [
      {
        "id_album": "2211858",
        "link_thumb": "https://live.staticflickr.com/65535/51670630320_226eb221b3_o.gif",
        "title": "Game"
      }
    ]
  },
  {
    "author": "LMB Studio",
    "link_thumb": "https://live.staticflickr.com/65535/51678304050_09ff640361_o.gif",
    "link_bin": "https://github.com/lmbstudiocontact/mb6_3/raw/main/PlantsVsZombies3_M6_2.bin",
    "id_bin": "PlantsVsZombies3_M6_2",
    "list_language": [
      {
        "author": "LMB Studio",
        "link_thumb": "https://live.staticflickr.com/65535/51677424711_4d41831287_o.gif",
        "link_bin": "https://github.com/lmbstudiocontact/mb6_3/raw/main/PlantsVsZombies3_M6_2_English.bin",
        "name_language": "PlantsVsZombies3_M6_2_English",
        "id_bin_language": "PlantsVsZombies3_M6_2_English"
      },
      {
        "author": "LMB Studio",
        "link_thumb": "https://live.staticflickr.com/65535/51678096249_439aa1083d_o.gif",
        "link_bin": "https://github.com/lmbstudiocontact/mb6_3/raw/main/PlantsVsZombies3_M6_2_Portuguese.bin",
        "name_language": "PlantsVsZombies3_M6_2_Portuguese",
        "id_bin_language": "PlantsVsZombies3_M6_2_Portuguese"
      },
      {
        "author": "LMB Studio",
        "link_thumb": "https://live.staticflickr.com/65535/51677425046_f7dfb785bd_o.gif",
        "link_bin": "https://github.com/lmbstudiocontact/mb6_3/raw/main/PlantsVsZombies3_M6_2_Russian.bin",
        "name_language": "PlantsVsZombies3_M6_2_Russian",
        "id_bin_language": "PlantsVsZombies3_M6_2_Russian"
      },
      {
        "author": "LMB Studio",
        "link_thumb": "https://live.staticflickr.com/65535/51677425341_37bd9494a5_o.gif",
        "link_bin": "https://github.com/lmbstudiocontact/mb6_3/raw/main/PlantsVsZombies3_M6_2_Spanish.bin",
        "name_language": "PlantsVsZombies3_M6_2_Spanish",
        "id_bin_language": "PlantsVsZombies3_M6_2_Spanish"
      }
    ],
    "array_tags": [],
    "list_album": [
      {
        "id_album": "-1038543655",
        "link_thumb": "https://live.staticflickr.com/65535/51678304050_09ff640361_o.gif",
        "title": "Plants Vs Zombies_M6_2"
      }
    ]
  },
  {
    "author": "LMB Studio",
    "link_thumb": "https://live.staticflickr.com/65535/51677538778_f261a2f49c_o.gif",
    "link_bin": "https://github.com/lmbstudiocontact/mb6_3/raw/main/OnePieceAnime36_M6_2.bin",
    "id_bin": "OnePieceAnime36_M6_2",
    "list_language": [
      {
        "author": "LMB Studio",
        "link_thumb": "https://live.staticflickr.com/65535/51678171490_a14c6c665e_o.gif",
        "link_bin": "https://github.com/lmbstudiocontact/mb6_3/raw/main/OnePieceAnime36_M6_2_English.bin",
        "name_language": "OnePieceAnime36_M6_2_English",
        "id_bin_language": "OnePieceAnime36_M6_2_English"
      },
      {
        "author": "LMB Studio",
        "link_thumb": "https://live.staticflickr.com/65535/51677963774_bd94de1c73_o.gif",
        "link_bin": "https://github.com/lmbstudiocontact/mb6_3/raw/main/OnePieceAnime36_M6_2_Portuguese.bin",
        "name_language": "OnePieceAnime36_M6_2_Portuguese",
        "id_bin_language": "OnePieceAnime36_M6_2_Portuguese"
      },
      {
        "author": "LMB Studio",
        "link_thumb": "https://live.staticflickr.com/65535/51678171900_239fc5350d_o.gif",
        "link_bin": "https://github.com/lmbstudiocontact/mb6_3/raw/main/OnePieceAnime36_M6_2_Russian.bin",
        "name_language": "OnePieceAnime36_M6_2_Russian",
        "id_bin_language": "OnePieceAnime36_M6_2_Russian"
      },
      {
        "author": "LMB Studio",
        "link_thumb": "https://live.staticflickr.com/65535/51678172190_4f69e2d577_o.gif",
        "link_bin": "https://github.com/lmbstudiocontact/mb6_3/raw/main/OnePieceAnime36_M6_2_Spanish.bin",
        "name_language": "OnePieceAnime36_M6_2_Spanish",
        "id_bin_language": "OnePieceAnime36_M6_2_Spanish"
      }
    ],
    "array_tags": [],
    "list_album": [
      {
        "id_album": "1669710643",
        "link_thumb": "https://live.staticflickr.com/65535/51677538778_f261a2f49c_o.gif",
        "title": "One Piece Anime_M6_2"
      }
    ]
  },
  {
    "author": "",
    "link_thumb": "https://live.staticflickr.com/65535/51670390545_2b3f6ec027_o.gif",
    "link_bin": "https://github.com/lmbstudiocontact/mb6_0/raw/main/1428.bin",
    "id_bin": "1428",
    "list_language": [],
    "array_tags": [
      "digital",
      "date",
      "distance",
      "heartrate",
      "calories",
      "battery",
      "steps"
    ],
    "list_album": [
      {
        "id_album": "2433880",
        "link_thumb": "https://live.staticflickr.com/65535/51670390545_2b3f6ec027_o.gif",
        "title": "None"
      }
    ]
  }
]