[
  {
    "author": "LMB Studio",
    "link_thumb": "https://live.staticflickr.com/65535/51677343885_6bf10b23a1_o.gif",
    "link_bin": "https://github.com/lmbstudiocontact/mb6_5/raw/main/CuteArt44_M6_2.bin",
    "id_bin": "CuteArt44_M6_2",
    "list_language": [
      {
        "author": "LMB Studio",
        "link_thumb": "https://live.staticflickr.com/65535/51676465966_590f5aec46_o.gif",
        "link_bin": "https://github.com/lmbstudiocontact/mb6_5/raw/main/CuteArt44_M6_2_English.bin",
        "name_language": "CuteArt44_M6_2_English",
        "id_bin_language": "CuteArt44_M6_2_English"
      },
      {
        "author": "LMB Studio",
        "link_thumb": "https://live.staticflickr.com/65535/51676466236_8b4e432374_o.gif",
        "link_bin": "https://github.com/lmbstudiocontact/mb6_5/raw/main/CuteArt44_M6_2_Portuguese.bin",
        "name_language": "CuteArt44_M6_2_Portuguese",
        "id_bin_language": "CuteArt44_M6_2_Portuguese"
      },
      {
        "author": "LMB Studio",
        "link_thumb": "https://live.staticflickr.com/65535/51675661827_7aa93c4368_o.gif",
        "link_bin": "https://github.com/lmbstudiocontact/mb6_5/raw/main/CuteArt44_M6_2_Russian.bin",
        "name_language": "CuteArt44_M6_2_Russian",
        "id_bin_language": "CuteArt44_M6_2_Russian"
      },
      {
        "author": "LMB Studio",
        "link_thumb": "https://live.staticflickr.com/65535/51676710918_96793af490_o.gif",
        "link_bin": "https://github.com/lmbstudiocontact/mb6_5/raw/main/CuteArt44_M6_2_Spanish.bin",
        "name_language": "CuteArt44_M6_2_Spanish",
        "id_bin_language": "CuteArt44_M6_2_Spanish"
      }
    ],
    "array_tags": [],
    "list_album": [
      {
        "id_album": "195512437",
        "link_thumb": "https://live.staticflickr.com/65535/51677343885_6bf10b23a1_o.gif",
        "title": "Cute Art_M6_2"
      }
    ]
  },
  {
    "author": "anhuituan",
    "link_thumb": "https://live.staticflickr.com/65535/51670586440_1022847e9d_o.gif",
    "link_bin": "https://github.com/lmbstudiocontact/mb6_0/raw/main/438.bin",
    "id_bin": "438",
    "list_language": [],
    "array_tags": [
      "analog",
      "anhuituan",
      "donghokim"
    ],
    "list_album": [
      {
        "id_album": "2433880",
        "link_thumb": "https://live.staticflickr.com/65535/51670586440_1022847e9d_o.gif",
        "title": "None"
      }
    ]
  },
  {
    "author": "ZanarkTempest",
    "link_thumb": "https://live.staticflickr.com/65535/51670328524_c7cf180395_o.gif",
    "link_bin": "https://github.com/lmbstudiocontact/mb6_1/raw/main/2304.bin",
    "id_bin": "2304",
    "list_language": [],
    "array_tags": [
      "heartrate",
      "hunterxhunter",
      "steps",
      "anime"
    ],
    "list_album": [
      {
        "id_album": "63410260",
        "link_thumb": "https://live.staticflickr.com/65535/51670328524_c7cf180395_o.gif",
        "title": "Anime"
      }
    ]
  },
  {
    "author": "ZanarkTempest",
    "link_thumb": "https://live.staticflickr.com/65535/51670519340_f46f55e91f_o.gif",
    "link_bin": "https://github.com/lmbstudiocontact/mb6_1/raw/main/2300.bin",
    "id_bin": "2300",
    "list_language": [],
    "array_tags": [
      "heartrate",
      "games",
      "steps"
    ],
    "list_album": [
      {
        "id_album": "63410260",
        "link_thumb": "https://live.staticflickr.com/65535/51670519340_f46f55e91f_o.gif",
        "title": "Anime"
      }
    ]
  },
  {
    "author": "LMB Studio",
    "link_thumb": "https://live.staticflickr.com/65535/51677055341_b1cffce7b6_o.gif",
    "link_bin": "https://github.com/lmbstudiocontact/mb6_7/raw/main/Kitty\u0026MyMelody74_M6_2.bin",
    "id_bin": "Kitty\u0026MyMelody74_M6_2",
    "list_language": [
      {
        "author": "LMB Studio",
        "link_thumb": "https://live.staticflickr.com/65535/51677936940_3c4a49dd6d_o.gif",
        "link_bin": "https://github.com/lmbstudiocontact/mb6_7/raw/main/Kitty\u0026MyMelody74_M6_2_English.bin",
        "name_language": "Kitty\u0026MyMelody74_M6_2_English",
        "id_bin_language": "Kitty\u0026MyMelody74_M6_2_English"
      },
      {
        "author": "LMB Studio",
        "link_thumb": "https://live.staticflickr.com/65535/51677055601_fbbe906330_o.gif",
        "link_bin": "https://github.com/lmbstudiocontact/mb6_7/raw/main/Kitty\u0026MyMelody74_M6_2_Portuguese.bin",
        "name_language": "Kitty\u0026MyMelody74_M6_2_Portuguese",
        "id_bin_language": "Kitty\u0026MyMelody74_M6_2_Portuguese"
      },
      {
        "author": "LMB Studio",
        "link_thumb": "https://live.staticflickr.com/65535/51676251407_0783d43c82_o.gif",
        "link_bin": "https://github.com/lmbstudiocontact/mb6_7/raw/main/Kitty\u0026MyMelody74_M6_2_Russian.bin",
        "name_language": "Kitty\u0026MyMelody74_M6_2_Russian",
        "id_bin_language": "Kitty\u0026MyMelody74_M6_2_Russian"
      },
      {
        "author": "LMB Studio",
        "link_thumb": "https://live.staticflickr.com/65535/51677303033_a1ed5b9741_o.gif",
        "link_bin": "https://github.com/lmbstudiocontact/mb6_7/raw/main/Kitty\u0026MyMelody74_M6_2_Spanish.bin",
        "name_language": "Kitty\u0026MyMelody74_M6_2_Spanish",
        "id_bin_language": "Kitty\u0026MyMelody74_M6_2_Spanish"
      }
    ],
    "array_tags": [],
    "list_album": [
      {
        "id_album": "1352454006",
        "link_thumb": "https://live.staticflickr.com/65535/51677055341_b1cffce7b6_o.gif",
        "title": "Kitty \u0026 My Melody_M6_2"
      }
    ]
  },
  {
    "author": "LMB Studio",
    "link_thumb": "https://live.staticflickr.com/65535/51677882645_544d1d8cdc_o.gif",
    "link_bin": "https://github.com/lmbstudiocontact/mb6_6/raw/main/Kitty\u0026MyMelody30_M6_2.bin",
    "id_bin": "Kitty\u0026MyMelody30_M6_2",
    "list_language": [
      {
        "author": "LMB Studio",
        "link_thumb": "https://live.staticflickr.com/65535/51677000956_f88f48de55_o.gif",
        "link_bin": "https://github.com/lmbstudiocontact/mb6_6/raw/main/Kitty\u0026MyMelody30_M6_2_English.bin",
        "name_language": "Kitty\u0026MyMelody30_M6_2_English",
        "id_bin_language": "Kitty\u0026MyMelody30_M6_2_English"
      },
      {
        "author": "LMB Studio",
        "link_thumb": "https://live.staticflickr.com/65535/51677673089_0193655d12_o.gif",
        "link_bin": "https://github.com/lmbstudiocontact/mb6_6/raw/main/Kitty\u0026MyMelody30_M6_2_Portuguese.bin",
        "name_language": "Kitty\u0026MyMelody30_M6_2_Portuguese",
        "id_bin_language": "Kitty\u0026MyMelody30_M6_2_Portuguese"
      },
      {
        "author": "LMB Studio",
        "link_thumb": "https://live.staticflickr.com/65535/51677883370_7cdedaff1b_o.gif",
        "link_bin": "https://github.com/lmbstudiocontact/mb6_6/raw/main/Kitty\u0026MyMelody30_M6_2_Russian.bin",
        "name_language": "Kitty\u0026MyMelody30_M6_2_Russian",
        "id_bin_language": "Kitty\u0026MyMelody30_M6_2_Russian"
      },
      {
        "author": "LMB Studio",
        "link_thumb": "https://live.staticflickr.com/65535/51677673539_07f1dd290b_o.gif",
        "link_bin": "https://github.com/lmbstudiocontact/mb6_6/raw/main/Kitty\u0026MyMelody30_M6_2_Spanish.bin",
        "name_language": "Kitty\u0026MyMelody30_M6_2_Spanish",
        "id_bin_language": "Kitty\u0026MyMelody30_M6_2_Spanish"
      }
    ],
    "array_tags": [],
    "list_album": [
      {
        "id_album": "1352454006",
        "link_thumb": "https://live.staticflickr.com/65535/51677882645_544d1d8cdc_o.gif",
        "title": "Kitty \u0026 My Melody_M6_2"
      }
    ]
  },
  {
    "author": "Rosta949",
    "link_thumb": "https://live.staticflickr.com/65535/51670130823_7dcb827eb0_o.gif",
    "link_bin": "https://github.com/lmbstudiocontact/mb6_1/raw/main/2347.bin",
    "id_bin": "2347",
    "list_language": [],
    "array_tags": [
      "digital",
      "date",
      "weekday",
      "time",
      "battery",
      "status",
      "animation"
    ],
    "list_album": [
      {
        "id_album": "2433880",
        "link_thumb": "https://live.staticflickr.com/65535/51670130823_7dcb827eb0_o.gif",
        "title": "None"
      }
    ]
  },
  {
    "author": "Blazedeck",
    "link_thumb": "https://live.staticflickr.com/65535/51668689327_1e14f1220e_o.gif",
    "link_bin": "https://github.com/lmbstudiocontact/mb6_0/raw/main/1258.bin",
    "id_bin": "1258",
    "list_language": [],
    "array_tags": [
      "date",
      "km",
      "game",
      "doomslayer",
      "doom",
      "calorias",
      "brasil",
      "calories",
      "battery",
      "steps",
      "red",
      "month",
      "quilometro",
      "pulse",
      "kilometer",
      "games",
      "pai",
      "portugues",
      "jogo",
      "day",
      "status"
    ],
    "list_album": [
      {
        "id_album": "2433880",
        "link_thumb": "https://live.staticflickr.com/65535/51668689327_1e14f1220e_o.gif",
        "title": "None"
      }
    ]
  },
  {
    "author": "gripka",
    "link_thumb": "https://live.staticflickr.com/65535/51668909612_4a67b6bd27_o.gif",
    "link_bin": "https://github.com/lmbstudiocontact/mb6_0/raw/main/434.bin",
    "id_bin": "434",
    "list_language": [],
    "array_tags": [
      "digital",
      "gripka",
      "brasil",
      "portugues",
      "mediatouch"
    ],
    "list_album": [
      {
        "id_album": "2433880",
        "link_thumb": "https://live.staticflickr.com/65535/51668909612_4a67b6bd27_o.gif",
        "title": "None"
      }
    ]
  },
  {
    "author": "SamRK",
    "link_thumb": "https://live.staticflickr.com/65535/51670414355_b6e3c1735e_o.gif",
    "link_bin": "https://github.com/lmbstudiocontact/mb6_0/raw/main/1646.bin",
    "id_bin": "1646",
    "list_language": [],
    "array_tags": [
      "date",
      "bluetooth",
      "pulse",
      "sot",
      "time",
      "battery",
      "steps"
    ],
    "list_album": [
      {
        "id_album": "2433880",
        "link_thumb": "https://live.staticflickr.com/65535/51670414355_b6e3c1735e_o.gif",
        "title": "None"
      }
    ]
  },
  {
    "author": "LMB Studio",
    "link_thumb": "https://live.staticflickr.com/65535/51677084773_ff8b96a1de_o.gif",
    "link_bin": "https://github.com/lmbstudiocontact/mb6_6/raw/main/HalloweenGhostWitch21_M6_2.bin",
    "id_bin": "HalloweenGhostWitch21_M6_2",
    "list_language": [
      {
        "author": "LMB Studio",
        "link_thumb": "https://live.staticflickr.com/65535/51677510404_9245f6fc87_o.gif",
        "link_bin": "https://github.com/lmbstudiocontact/mb6_6/raw/main/HalloweenGhostWitch21_M6_2_English.bin",
        "name_language": "HalloweenGhostWitch21_M6_2_English",
        "id_bin_language": "HalloweenGhostWitch21_M6_2_English"
      },
      {
        "author": "LMB Studio",
        "link_thumb": "https://live.staticflickr.com/65535/51677085303_dafc2cb321_o.gif",
        "link_bin": "https://github.com/lmbstudiocontact/mb6_6/raw/main/HalloweenGhostWitch21_M6_2_Portuguese.bin",
        "name_language": "HalloweenGhostWitch21_M6_2_Portuguese",
        "id_bin_language": "HalloweenGhostWitch21_M6_2_Portuguese"
      },
      {
        "author": "LMB Studio",
        "link_thumb": "https://live.staticflickr.com/65535/51677085588_6c5fe3d3cd_o.gif",
        "link_bin": "https://github.com/lmbstudiocontact/mb6_6/raw/main/HalloweenGhostWitch21_M6_2_Russian.bin",
        "name_language": "HalloweenGhostWitch21_M6_2_Russian",
        "id_bin_language": "HalloweenGhostWitch21_M6_2_Russian"
      },
      {
        "author": "LMB Studio",
        "link_thumb": "https://live.staticflickr.com/65535/51677721225_f900806ee5_o.gif",
        "link_bin": "https://github.com/lmbstudiocontact/mb6_6/raw/main/HalloweenGhostWitch21_M6_2_Spanish.bin",
        "name_language": "HalloweenGhostWitch21_M6_2_Spanish",
        "id_bin_language": "HalloweenGhostWitch21_M6_2_Spanish"
      }
    ],
    "array_tags": [],
    "list_album": [
      {
        "id_album": "-877220232",
        "link_thumb": "https://live.staticflickr.com/65535/51677084773_ff8b96a1de_o.gif",
        "title": "Halloween Ghost Witch_M6_2"
      }
    ]
  },
  {
    "author": "q10243732",
    "link_thumb": "https://live.staticflickr.com/65535/51670462295_28c077e141_o.gif",
    "link_bin": "https://github.com/lmbstudiocontact/mb6_1/raw/main/1929.bin",
    "id_bin": "1929",
    "list_language": [],
    "array_tags": [
      "date",
      "taylorswift",
      "weather",
      "battery",
      "steps"
    ],
    "list_album": [
      {
        "id_album": "2433880",
        "link_thumb": "https://live.staticflickr.com/65535/51670462295_28c077e141_o.gif",
        "title": "None"
      }
    ]
  },
  {
    "author": "Rahmaniardi",
    "link_thumb": "https://live.staticflickr.com/65535/51670384780_7563c56035_o.gif",
    "link_bin": "https://github.com/lmbstudiocontact/mb6_0/raw/main/1381.bin",
    "id_bin": "1381",
    "list_language": [],
    "array_tags": [
      "digimon"
    ],
    "list_album": [
      {
        "id_album": "63410260",
        "link_thumb": "https://live.staticflickr.com/65535/51670384780_7563c56035_o.gif",
        "title": "Anime"
      }
    ]
  },
  {
    "author": "impactopdesign",
    "link_thumb": "https://live.staticflickr.com/65535/51670581840_ee2725e1aa_o.gif",
    "link_bin": "https://github.com/lmbstudiocontact/mb6_0/raw/main/405.bin",
    "id_bin": "405",
    "list_language": [],
    "array_tags": [
      "digital",
      "soccer",
      "inter",
      "reds",
      "futebol",
      "colorado",
      "internacional"
    ],
    "list_album": [
      {
        "id_album": "2433880",
        "link_thumb": "https://live.staticflickr.com/65535/51670581840_ee2725e1aa_o.gif",
        "title": "None"
      }
    ]
  },
  {
    "author": "kutuzov",
    "link_thumb": "https://live.staticflickr.com/65535/51670220284_c56f4cd006_o.gif",
    "link_bin": "https://github.com/lmbstudiocontact/mb6_0/raw/main/1635.bin",
    "id_bin": "1635",
    "list_language": [],
    "array_tags": [
      "date",
      "digital",
      "battery"
    ],
    "list_album": [
      {
        "id_album": "2433880",
        "link_thumb": "https://live.staticflickr.com/65535/51670220284_c56f4cd006_o.gif",
        "title": "None"
      }
    ]
  },
  {
    "author": "ZanarkTempest",
    "link_thumb": "https://live.staticflickr.com/65535/51670321219_302c363d9a_o.gif",
    "link_bin": "https://github.com/lmbstudiocontact/mb6_1/raw/main/2275.bin",
    "id_bin": "2275",
    "list_language": [],
    "array_tags": [
      "donald",
      "goofy",
      "cartoon",
      "disney",
      "heartrate",
      "steps",
      "mickey"
    ],
    "list_album": [
      {
        "id_album": "-2075887794",
        "link_thumb": "https://live.staticflickr.com/65535/51670321219_302c363d9a_o.gif",
        "title": "Cartoon"
      }
    ]
  },
  {
    "author": "LMB Studio",
    "link_thumb": "https://live.staticflickr.com/65535/51676174512_455630b591_o.gif",
    "link_bin": "https://github.com/lmbstudiocontact/mb6_6/raw/main/Kitty\u0026MyMelody13_M6_2.bin",
    "id_bin": "Kitty\u0026MyMelody13_M6_2",
    "list_language": [
      {
        "author": "LMB Studio",
        "link_thumb": "https://live.staticflickr.com/65535/51676174867_90441eb919_o.gif",
        "link_bin": "https://github.com/lmbstudiocontact/mb6_6/raw/main/Kitty\u0026MyMelody13_M6_2_English.bin",
        "name_language": "Kitty\u0026MyMelody13_M6_2_English",
        "id_bin_language": "Kitty\u0026MyMelody13_M6_2_English"
      },
      {
        "author": "LMB Studio",
        "link_thumb": "https://live.staticflickr.com/65535/51677860730_a7dcdb118a_o.gif",
        "link_bin": "https://github.com/lmbstudiocontact/mb6_6/raw/main/Kitty\u0026MyMelody13_M6_2_Portuguese.bin",
        "name_language": "Kitty\u0026MyMelody13_M6_2_Portuguese",
        "id_bin_language": "Kitty\u0026MyMelody13_M6_2_Portuguese"
      },
      {
        "author": "LMB Studio",
        "link_thumb": "https://live.staticflickr.com/65535/51677861000_3d2c6a3f3d_o.gif",
        "link_bin": "https://github.com/lmbstudiocontact/mb6_6/raw/main/Kitty\u0026MyMelody13_M6_2_Russian.bin",
        "name_language": "Kitty\u0026MyMelody13_M6_2_Russian",
        "id_bin_language": "Kitty\u0026MyMelody13_M6_2_Russian"
      },
      {
        "author": "LMB Studio",
        "link_thumb": "https://live.staticflickr.com/65535/51677861200_8796cbb155_o.gif",
        "link_bin": "https://github.com/lmbstudiocontact/mb6_6/raw/main/Kitty\u0026MyMelody13_M6_2_Spanish.bin",
        "name_language": "Kitty\u0026MyMelody13_M6_2_Spanish",
        "id_bin_language": "Kitty\u0026MyMelody13_M6_2_Spanish"
      }
    ],
    "array_tags": [],
    "list_album": [
      {
        "id_album": "1352454006",
        "link_thumb": "https://live.staticflickr.com/65535/51676174512_455630b591_o.gif",
        "title": "Kitty \u0026 My Melody_M6_2"
      }
    ]
  },
  {
    "author": "LMB Studio",
    "link_thumb": "https://live.staticflickr.com/65535/51678054909_f1481af035_o.gif",
    "link_bin": "https://github.com/lmbstudiocontact/mb6_3/raw/main/Onmyoji20_M6_2.bin",
    "id_bin": "Onmyoji20_M6_2",
    "list_language": [
      {
        "author": "LMB Studio",
        "link_thumb": "https://live.staticflickr.com/65535/51678055199_2b52307c57_o.gif",
        "link_bin": "https://github.com/lmbstudiocontact/mb6_3/raw/main/Onmyoji20_M6_2_English.bin",
        "name_language": "Onmyoji20_M6_2_English",
        "id_bin_language": "Onmyoji20_M6_2_English"
      },
      {
        "author": "LMB Studio",
        "link_thumb": "https://live.staticflickr.com/65535/51677631003_a9bbe788da_o.gif",
        "link_bin": "https://github.com/lmbstudiocontact/mb6_3/raw/main/Onmyoji20_M6_2_Portuguese.bin",
        "name_language": "Onmyoji20_M6_2_Portuguese",
        "id_bin_language": "Onmyoji20_M6_2_Portuguese"
      },
      {
        "author": "LMB Studio",
        "link_thumb": "https://live.staticflickr.com/65535/51678055649_d0c9b44069_o.gif",
        "link_bin": "https://github.com/lmbstudiocontact/mb6_3/raw/main/Onmyoji20_M6_2_Russian.bin",
        "name_language": "Onmyoji20_M6_2_Russian",
        "id_bin_language": "Onmyoji20_M6_2_Russian"
      },
      {
        "author": "LMB Studio",
        "link_thumb": "https://live.staticflickr.com/65535/51678055989_682ac54ab1_o.gif",
        "link_bin": "https://github.com/lmbstudiocontact/mb6_3/raw/main/Onmyoji20_M6_2_Spanish.bin",
        "name_language": "Onmyoji20_M6_2_Spanish",
        "id_bin_language": "Onmyoji20_M6_2_Spanish"
      }
    ],
    "array_tags": [],
    "list_album": [
      {
        "id_album": "473358232",
        "link_thumb": "https://live.staticflickr.com/65535/51678054909_f1481af035_o.gif",
        "title": "Onmyoji_M6_2"
      }
    ]
  },
  {
    "author": "ZanarkTempest",
    "link_thumb": "https://live.staticflickr.com/65535/51669881048_5b477bec04_o.gif",
    "link_bin": "https://github.com/lmbstudiocontact/mb6_1/raw/main/2298.bin",
    "id_bin": "2298",
    "list_language": [],
    "array_tags": [
      "heartrate",
      "games",
      "steps"
    ],
    "list_album": [
      {
        "id_album": "2211858",
        "link_thumb": "https://live.staticflickr.com/65535/51669881048_5b477bec04_o.gif",
        "title": "Game"
      }
    ]
  },
  {
    "author": "ZanarkTempest",
    "link_thumb": "https://live.staticflickr.com/65535/51669600786_2229e3b83e_o.gif",
    "link_bin": "https://github.com/lmbstudiocontact/mb6_1/raw/main/2054.bin",
    "id_bin": "2054",
    "list_language": [],
    "array_tags": [
      "nintendo"
    ],
    "list_album": [
      {
        "id_album": "2211858",
        "link_thumb": "https://live.staticflickr.com/65535/51669600786_2229e3b83e_o.gif",
        "title": "Game"
      }
    ]
  },
  {
    "author": "LMB Studio",
    "link_thumb": "https://live.staticflickr.com/65535/51678460245_0f6e9fc555_o.gif",
    "link_bin": "https://github.com/lmbstudiocontact/mb6_4/raw/main/Rio210_M6_2.bin",
    "id_bin": "Rio210_M6_2",
    "list_language": [
      {
        "author": "LMB Studio",
        "link_thumb": "https://live.staticflickr.com/65535/51677829253_2594ce1203_o.gif",
        "link_bin": "https://github.com/lmbstudiocontact/mb6_4/raw/main/Rio210_M6_2_English.bin",
        "name_language": "Rio210_M6_2_English",
        "id_bin_language": "Rio210_M6_2_English"
      },
      {
        "author": "LMB Studio",
        "link_thumb": "https://live.staticflickr.com/65535/51678460555_59eed74792_o.gif",
        "link_bin": "https://github.com/lmbstudiocontact/mb6_4/raw/main/Rio210_M6_2_Portuguese.bin",
        "name_language": "Rio210_M6_2_Portuguese",
        "id_bin_language": "Rio210_M6_2_Portuguese"
      },
      {
        "author": "LMB Studio",
        "link_thumb": "https://live.staticflickr.com/65535/51677581586_0b3eb60c0f_o.gif",
        "link_bin": "https://github.com/lmbstudiocontact/mb6_4/raw/main/Rio210_M6_2_Russian.bin",
        "name_language": "Rio210_M6_2_Russian",
        "id_bin_language": "Rio210_M6_2_Russian"
      },
      {
        "author": "LMB Studio",
        "link_thumb": "https://live.staticflickr.com/65535/51676774952_2f283af268_o.gif",
        "link_bin": "https://github.com/lmbstudiocontact/mb6_4/raw/main/Rio210_M6_2_Spanish.bin",
        "name_language": "Rio210_M6_2_Spanish",
        "id_bin_language": "Rio210_M6_2_Spanish"
      }
    ],
    "array_tags": [],
    "list_album": [
      {
        "id_album": "296910609",
        "link_thumb": "https://live.staticflickr.com/65535/51678460245_0f6e9fc555_o.gif",
        "title": "Rio 2_M6_2"
      }
    ]
  },
  {
    "author": "LMB Studio",
    "link_thumb": "https://live.staticflickr.com/65535/51678151145_337a1165a0_o.gif",
    "link_bin": "https://github.com/lmbstudiocontact/mb6_3/raw/main/OnePieceAnime18_M6_2.bin",
    "id_bin": "OnePieceAnime18_M6_2",
    "list_language": [
      {
        "author": "LMB Studio",
        "link_thumb": "https://live.staticflickr.com/65535/51678151355_d3b2919f51_o.gif",
        "link_bin": "https://github.com/lmbstudiocontact/mb6_3/raw/main/OnePieceAnime18_M6_2_English.bin",
        "name_language": "OnePieceAnime18_M6_2_English",
        "id_bin_language": "OnePieceAnime18_M6_2_English"
      },
      {
        "author": "LMB Studio",
        "link_thumb": "https://live.staticflickr.com/65535/51677518843_cc21e6bed7_o.gif",
        "link_bin": "https://github.com/lmbstudiocontact/mb6_3/raw/main/OnePieceAnime18_M6_2_Portuguese.bin",
        "name_language": "OnePieceAnime18_M6_2_Portuguese",
        "id_bin_language": "OnePieceAnime18_M6_2_Portuguese"
      },
      {
        "author": "LMB Studio",
        "link_thumb": "https://live.staticflickr.com/65535/51678151660_29a9a616e3_o.gif",
        "link_bin": "https://github.com/lmbstudiocontact/mb6_3/raw/main/OnePieceAnime18_M6_2_Russian.bin",
        "name_language": "OnePieceAnime18_M6_2_Russian",
        "id_bin_language": "OnePieceAnime18_M6_2_Russian"
      },
      {
        "author": "LMB Studio",
        "link_thumb": "https://live.staticflickr.com/65535/51677944164_f04e3c26ab_o.gif",
        "link_bin": "https://github.com/lmbstudiocontact/mb6_3/raw/main/OnePieceAnime18_M6_2_Spanish.bin",
        "name_language": "OnePieceAnime18_M6_2_Spanish",
        "id_bin_language": "OnePieceAnime18_M6_2_Spanish"
      }
    ],
    "array_tags": [],
    "list_album": [
      {
        "id_album": "1669710643",
        "link_thumb": "https://live.staticflickr.com/65535/51678151145_337a1165a0_o.gif",
        "title": "One Piece Anime_M6_2"
      }
    ]
  },
  {
    "author": "ZanarkTempest",
    "link_thumb": "https://live.staticflickr.com/65535/51668765077_cffd51c6a4_o.gif",
    "link_bin": "https://github.com/lmbstudiocontact/mb6_1/raw/main/1809.bin",
    "id_bin": "1809",
    "list_language": [],
    "array_tags": [
      "naruto",
      "anime"
    ],
    "list_album": [
      {
        "id_album": "63410260",
        "link_thumb": "https://live.staticflickr.com/65535/51668765077_cffd51c6a4_o.gif",
        "title": "Anime"
      }
    ]
  },
  {
    "author": "zyfish",
    "link_thumb": "https://live.staticflickr.com/65535/51668779442_033ae1d4de_o.gif",
    "link_bin": "https://github.com/lmbstudiocontact/mb6_0/raw/main/19.bin",
    "id_bin": "19",
    "list_language": [],
    "array_tags": [
      "digital",
      "date",
      "weather",
      "battery",
      "steps"
    ],
    "list_album": [
      {
        "id_album": "2433880",
        "link_thumb": "https://live.staticflickr.com/65535/51668779442_033ae1d4de_o.gif",
        "title": "None"
      }
    ]
  },
  {
    "author": "nbert",
    "link_thumb": "https://live.staticflickr.com/65535/51670353694_e44e01c2a4_o.gif",
    "link_bin": "https://github.com/lmbstudiocontact/mb6_0/raw/main/256.bin",
    "id_bin": "256",
    "list_language": [],
    "array_tags": [
      "date",
      "minimal",
      "heartrate",
      "weather",
      "time",
      "day",
      "wind"
    ],
    "list_album": [
      {
        "id_album": "2433880",
        "link_thumb": "https://live.staticflickr.com/65535/51670353694_e44e01c2a4_o.gif",
        "title": "None"
      }
    ]
  },
  {
    "author": "Zdan",
    "link_thumb": "https://live.staticflickr.com/65535/51670381305_f9464e7b88_o.gif",
    "link_bin": "https://github.com/lmbstudiocontact/mb6_0/raw/main/1363.bin",
    "id_bin": "1363",
    "list_language": [],
    "array_tags": [
      "date",
      "distance",
      "watch",
      "alarm",
      "pulse",
      "calories",
      "battery",
      "day",
      "steps"
    ],
    "list_album": [
      {
        "id_album": "2433880",
        "link_thumb": "https://live.staticflickr.com/65535/51670381305_f9464e7b88_o.gif",
        "title": "None"
      }
    ]
  },
  {
    "author": "LMB Studio",
    "link_thumb": "https://live.staticflickr.com/65535/51678502105_f6f077e9e2_o.gif",
    "link_bin": "https://github.com/lmbstudiocontact/mb6_4/raw/main/SevendeadlysinsAnime35_M6_2.bin",
    "id_bin": "SevendeadlysinsAnime35_M6_2",
    "list_language": [
      {
        "author": "LMB Studio",
        "link_thumb": "https://live.staticflickr.com/65535/51678294839_d73da4ab76_o.gif",
        "link_bin": "https://github.com/lmbstudiocontact/mb6_4/raw/main/SevendeadlysinsAnime35_M6_2_English.bin",
        "name_language": "SevendeadlysinsAnime35_M6_2_English",
        "id_bin_language": "SevendeadlysinsAnime35_M6_2_English"
      },
      {
        "author": "LMB Studio",
        "link_thumb": "https://live.staticflickr.com/65535/51678295004_cb55bb7a7c_o.gif",
        "link_bin": "https://github.com/lmbstudiocontact/mb6_4/raw/main/SevendeadlysinsAnime35_M6_2_Portuguese.bin",
        "name_language": "SevendeadlysinsAnime35_M6_2_Portuguese",
        "id_bin_language": "SevendeadlysinsAnime35_M6_2_Portuguese"
      },
      {
        "author": "LMB Studio",
        "link_thumb": "https://live.staticflickr.com/65535/51677623066_f93731d7f2_o.gif",
        "link_bin": "https://github.com/lmbstudiocontact/mb6_4/raw/main/SevendeadlysinsAnime35_M6_2_Russian.bin",
        "name_language": "SevendeadlysinsAnime35_M6_2_Russian",
        "id_bin_language": "SevendeadlysinsAnime35_M6_2_Russian"
      },
      {
        "author": "LMB Studio",
        "link_thumb": "https://live.staticflickr.com/65535/51678295294_45971d67a6_o.gif",
        "link_bin": "https://github.com/lmbstudiocontact/mb6_4/raw/main/SevendeadlysinsAnime35_M6_2_Spanish.bin",
        "name_language": "SevendeadlysinsAnime35_M6_2_Spanish",
        "id_bin_language": "SevendeadlysinsAnime35_M6_2_Spanish"
      }
    ],
    "array_tags": [],
    "list_album": [
      {
        "id_album": "1052927760",
        "link_thumb": "https://live.staticflickr.com/65535/51678502105_f6f077e9e2_o.gif",
        "title": "Seven deadly sins Anime_M6_2"
      }
    ]
  },
  {
    "author": "joaokit",
    "link_thumb": "https://live.staticflickr.com/65535/51670369134_de0d5b85ef_o.gif",
    "link_bin": "https://github.com/lmbstudiocontact/mb6_0/raw/main/322.bin",
    "id_bin": "322",
    "list_language": [],
    "array_tags": [
      "date",
      "apple",
      "heartrate",
      "english",
      "ios",
      "watchos"
    ],
    "list_album": [
      {
        "id_album": "-2075887794",
        "link_thumb": "https://live.staticflickr.com/65535/51670369134_de0d5b85ef_o.gif",
        "title": "Cartoon"
      }
    ]
  },
  {
    "author": "ZanarkTempest",
    "link_thumb": "https://live.staticflickr.com/65535/51668803237_bbe6c1cb92_o.gif",
    "link_bin": "https://github.com/lmbstudiocontact/mb6_1/raw/main/2058.bin",
    "id_bin": "2058",
    "list_language": [],
    "array_tags": [
      "game",
      "anime",
      "ryu"
    ],
    "list_album": [
      {
        "id_album": "2211858",
        "link_thumb": "https://live.staticflickr.com/65535/51668803237_bbe6c1cb92_o.gif",
        "title": "Game"
      }
    ]
  },
  {
    "author": "LMB Studio",
    "link_thumb": "https://live.staticflickr.com/65535/51677094486_4c4e8880ae_o.gif",
    "link_bin": "https://github.com/lmbstudiocontact/mb6_7/raw/main/Lilo\u0026StitchCartoon8_M6_2.bin",
    "id_bin": "Lilo\u0026StitchCartoon8_M6_2",
    "list_language": [
      {
        "author": "LMB Studio",
        "link_thumb": "https://live.staticflickr.com/65535/51676289687_0d18ab9dc4_o.gif",
        "link_bin": "https://github.com/lmbstudiocontact/mb6_7/raw/main/Lilo\u0026StitchCartoon8_M6_2_English.bin",
        "name_language": "Lilo\u0026StitchCartoon8_M6_2_English",
        "id_bin_language": "Lilo\u0026StitchCartoon8_M6_2_English"
      },
      {
        "author": "LMB Studio",
        "link_thumb": "https://live.staticflickr.com/65535/51677094921_9b0a3a125d_o.gif",
        "link_bin": "https://github.com/lmbstudiocontact/mb6_7/raw/main/Lilo\u0026StitchCartoon8_M6_2_Portuguese.bin",
        "name_language": "Lilo\u0026StitchCartoon8_M6_2_Portuguese",
        "id_bin_language": "Lilo\u0026StitchCartoon8_M6_2_Portuguese"
      },
      {
        "author": "LMB Studio",
        "link_thumb": "https://live.staticflickr.com/65535/51676290157_8f50d90e99_o.gif",
        "link_bin": "https://github.com/lmbstudiocontact/mb6_7/raw/main/Lilo\u0026StitchCartoon8_M6_2_Russian.bin",
        "name_language": "Lilo\u0026StitchCartoon8_M6_2_Russian",
        "id_bin_language": "Lilo\u0026StitchCartoon8_M6_2_Russian"
      },
      {
        "author": "LMB Studio",
        "link_thumb": "https://live.staticflickr.com/65535/51676290367_8819600f6a_o.gif",
        "link_bin": "https://github.com/lmbstudiocontact/mb6_7/raw/main/Lilo\u0026StitchCartoon8_M6_2_Spanish.bin",
        "name_language": "Lilo\u0026StitchCartoon8_M6_2_Spanish",
        "id_bin_language": "Lilo\u0026StitchCartoon8_M6_2_Spanish"
      }
    ],
    "array_tags": [],
    "list_album": [
      {
        "id_album": "1677497602",
        "link_thumb": "https://live.staticflickr.com/65535/51677094486_4c4e8880ae_o.gif",
        "title": "Lilo \u0026 Stitch Cartoon_M6_2"
      }
    ]
  },
  {
    "author": "LMB Studio",
    "link_thumb": "https://live.staticflickr.com/65535/51677246634_ddf9f9fa67_o.gif",
    "link_bin": "https://github.com/lmbstudiocontact/mb6_5/raw/main/DisneyCartoon38_M6_2.bin",
    "id_bin": "DisneyCartoon38_M6_2",
    "list_language": [
      {
        "author": "LMB Studio",
        "link_thumb": "https://live.staticflickr.com/65535/51677246964_baa6a3f4e6_o.gif",
        "link_bin": "https://github.com/lmbstudiocontact/mb6_5/raw/main/DisneyCartoon38_M6_2_English.bin",
        "name_language": "DisneyCartoon38_M6_2_English",
        "id_bin_language": "DisneyCartoon38_M6_2_English"
      },
      {
        "author": "LMB Studio",
        "link_thumb": "https://live.staticflickr.com/65535/51675770742_999d493470_o.gif",
        "link_bin": "https://github.com/lmbstudiocontact/mb6_5/raw/main/DisneyCartoon38_M6_2_Portuguese.bin",
        "name_language": "DisneyCartoon38_M6_2_Portuguese",
        "id_bin_language": "DisneyCartoon38_M6_2_Portuguese"
      },
      {
        "author": "LMB Studio",
        "link_thumb": "https://live.staticflickr.com/65535/51676820488_7b89fdfc86_o.gif",
        "link_bin": "https://github.com/lmbstudiocontact/mb6_5/raw/main/DisneyCartoon38_M6_2_Russian.bin",
        "name_language": "DisneyCartoon38_M6_2_Russian",
        "id_bin_language": "DisneyCartoon38_M6_2_Russian"
      },
      {
        "author": "LMB Studio",
        "link_thumb": "https://live.staticflickr.com/65535/51676820773_c66011b4d6_o.gif",
        "link_bin": "https://github.com/lmbstudiocontact/mb6_5/raw/main/DisneyCartoon38_M6_2_Spanish.bin",
        "name_language": "DisneyCartoon38_M6_2_Spanish",
        "id_bin_language": "DisneyCartoon38_M6_2_Spanish"
      }
    ],
    "array_tags": [],
    "list_album": [
      {
        "id_album": "-1858058375",
        "link_thumb": "https://live.staticflickr.com/65535/51677246634_ddf9f9fa67_o.gif",
        "title": "Disney Cartoon_M6_2"
      }
    ]
  },
  {
    "author": "LMB Studio",
    "link_thumb": "https://live.staticflickr.com/65535/51676835118_5480e5f49b_o.gif",
    "link_bin": "https://github.com/lmbstudiocontact/mb6_5/raw/main/DisneyCartoon49_M6_2.bin",
    "id_bin": "DisneyCartoon49_M6_2",
    "list_language": [
      {
        "author": "LMB Studio",
        "link_thumb": "https://live.staticflickr.com/65535/51676835453_7463fcbf47_o.gif",
        "link_bin": "https://github.com/lmbstudiocontact/mb6_5/raw/main/DisneyCartoon49_M6_2_English.bin",
        "name_language": "DisneyCartoon49_M6_2_English",
        "id_bin_language": "DisneyCartoon49_M6_2_English"
      },
      {
        "author": "LMB Studio",
        "link_thumb": "https://live.staticflickr.com/65535/51677469995_3b968780ca_o.gif",
        "link_bin": "https://github.com/lmbstudiocontact/mb6_5/raw/main/DisneyCartoon49_M6_2_Portuguese.bin",
        "name_language": "DisneyCartoon49_M6_2_Portuguese",
        "id_bin_language": "DisneyCartoon49_M6_2_Portuguese"
      },
      {
        "author": "LMB Studio",
        "link_thumb": "https://live.staticflickr.com/65535/51676835893_0e29bd5209_o.gif",
        "link_bin": "https://github.com/lmbstudiocontact/mb6_5/raw/main/DisneyCartoon49_M6_2_Russian.bin",
        "name_language": "DisneyCartoon49_M6_2_Russian",
        "id_bin_language": "DisneyCartoon49_M6_2_Russian"
      },
      {
        "author": "LMB Studio",
        "link_thumb": "https://live.staticflickr.com/65535/51677470525_90ddfddf47_o.gif",
        "link_bin": "https://github.com/lmbstudiocontact/mb6_5/raw/main/DisneyCartoon49_M6_2_Spanish.bin",
        "name_language": "DisneyCartoon49_M6_2_Spanish",
        "id_bin_language": "DisneyCartoon49_M6_2_Spanish"
      }
    ],
    "array_tags": [],
    "list_album": [
      {
        "id_album": "-1858058375",
        "link_thumb": "https://live.staticflickr.com/65535/51676835118_5480e5f49b_o.gif",
        "title": "Disney Cartoon_M6_2"
      }
    ]
  },
  {
    "author": "LMB Studio",
    "link_thumb": "https://live.staticflickr.com/65535/51676692797_cf4d0541de_o.gif",
    "link_bin": "https://github.com/lmbstudiocontact/mb6_9/raw/main/PokmonAnime62_M6_2.bin",
    "id_bin": "PokmonAnime62_M6_2",
    "list_language": [
      {
        "author": "LMB Studio",
        "link_thumb": "https://live.staticflickr.com/65535/51678170949_c93026ca91_o.gif",
        "link_bin": "https://github.com/lmbstudiocontact/mb6_9/raw/main/PokmonAnime62_M6_2_English.bin",
        "name_language": "PokmonAnime62_M6_2_English",
        "id_bin_language": "PokmonAnime62_M6_2_English"
      },
      {
        "author": "LMB Studio",
        "link_thumb": "https://live.staticflickr.com/65535/51677499691_96c2bc2c85_o.gif",
        "link_bin": "https://github.com/lmbstudiocontact/mb6_9/raw/main/PokmonAnime62_M6_2_Portuguese.bin",
        "name_language": "PokmonAnime62_M6_2_Portuguese",
        "id_bin_language": "PokmonAnime62_M6_2_Portuguese"
      },
      {
        "author": "LMB Studio",
        "link_thumb": "https://live.staticflickr.com/65535/51677748238_6d0f5d5f1d_o.gif",
        "link_bin": "https://github.com/lmbstudiocontact/mb6_9/raw/main/PokmonAnime62_M6_2_Russian.bin",
        "name_language": "PokmonAnime62_M6_2_Russian",
        "id_bin_language": "PokmonAnime62_M6_2_Russian"
      },
      {
        "author": "LMB Studio",
        "link_thumb": "https://live.staticflickr.com/65535/51677500231_200e4ba51d_o.gif",
        "link_bin": "https://github.com/lmbstudiocontact/mb6_9/raw/main/PokmonAnime62_M6_2_Spanish.bin",
        "name_language": "PokmonAnime62_M6_2_Spanish",
        "id_bin_language": "PokmonAnime62_M6_2_Spanish"
      }
    ],
    "array_tags": [],
    "list_album": [
      {
        "id_album": "-1571020089",
        "link_thumb": "https://live.staticflickr.com/65535/51676692797_cf4d0541de_o.gif",
        "title": "Pokmon Anime_M6_2"
      }
    ]
  },
  {
    "author": "LMB Studio",
    "link_thumb": "https://live.staticflickr.com/65535/51677114989_57ef040f9e_o.gif",
    "link_bin": "https://github.com/lmbstudiocontact/mb6_8/raw/main/CuteArt25_M6_2.bin",
    "id_bin": "CuteArt25_M6_2",
    "list_language": [
      {
        "author": "LMB Studio",
        "link_thumb": "https://live.staticflickr.com/65535/51677320830_babc11af86_o.gif",
        "link_bin": "https://github.com/lmbstudiocontact/mb6_8/raw/main/CuteArt25_M6_2_English.bin",
        "name_language": "CuteArt25_M6_2_English",
        "id_bin_language": "CuteArt25_M6_2_English"
      },
      {
        "author": "LMB Studio",
        "link_thumb": "https://live.staticflickr.com/65535/51676687168_3e2c2a72f1_o.gif",
        "link_bin": "https://github.com/lmbstudiocontact/mb6_8/raw/main/CuteArt25_M6_2_Portuguese.bin",
        "name_language": "CuteArt25_M6_2_Portuguese",
        "id_bin_language": "CuteArt25_M6_2_Portuguese"
      },
      {
        "author": "LMB Studio",
        "link_thumb": "https://live.staticflickr.com/65535/51677115544_5516b6a771_o.gif",
        "link_bin": "https://github.com/lmbstudiocontact/mb6_8/raw/main/CuteArt25_M6_2_Russian.bin",
        "name_language": "CuteArt25_M6_2_Russian",
        "id_bin_language": "CuteArt25_M6_2_Russian"
      },
      {
        "author": "LMB Studio",
        "link_thumb": "https://live.staticflickr.com/65535/51676443151_842726b96a_o.gif",
        "link_bin": "https://github.com/lmbstudiocontact/mb6_8/raw/main/CuteArt25_M6_2_Spanish.bin",
        "name_language": "CuteArt25_M6_2_Spanish",
        "id_bin_language": "CuteArt25_M6_2_Spanish"
      }
    ],
    "array_tags": [],
    "list_album": [
      {
        "id_album": "195512437",
        "link_thumb": "https://live.staticflickr.com/65535/51677114989_57ef040f9e_o.gif",
        "title": "Cute Art_M6_2"
      }
    ]
  },
  {
    "author": "PsychoMatt",
    "link_thumb": "https://live.staticflickr.com/65535/51670153709_3de5f155d7_o.gif",
    "link_bin": "https://github.com/lmbstudiocontact/mb6_0/raw/main/1054.bin",
    "id_bin": "1054",
    "list_language": [],
    "array_tags": [
      "digital",
      "date",
      "distance",
      "battery",
      "steps",
      "kcal",
      "bluetooth",
      "pulse",
      "weather",
      "alarm",
      "lock",
      "dnd",
      "status"
    ],
    "list_album": [
      {
        "id_album": "2433880",
        "link_thumb": "https://live.staticflickr.com/65535/51670153709_3de5f155d7_o.gif",
        "title": "None"
      }
    ]
  },
  {
    "author": "LMB Studio",
    "link_thumb": "https://live.staticflickr.com/65535/51676703881_f65d97d559_o.gif",
    "link_bin": "https://github.com/lmbstudiocontact/mb6_2/raw/main/DragonBallAnime50_M6_2.bin",
    "id_bin": "DragonBallAnime50_M6_2",
    "list_language": [
      {
        "author": "LMB Studio",
        "link_thumb": "https://live.staticflickr.com/65535/51677585875_63a5f0b50e_o.gif",
        "link_bin": "https://github.com/lmbstudiocontact/mb6_2/raw/main/DragonBallAnime50_M6_2_English.bin",
        "name_language": "DragonBallAnime50_M6_2_English",
        "id_bin_language": "DragonBallAnime50_M6_2_English"
      },
      {
        "author": "LMB Studio",
        "link_thumb": "https://live.staticflickr.com/65535/51677586025_606a780219_o.gif",
        "link_bin": "https://github.com/lmbstudiocontact/mb6_2/raw/main/DragonBallAnime50_M6_2_Portuguese.bin",
        "name_language": "DragonBallAnime50_M6_2_Portuguese",
        "id_bin_language": "DragonBallAnime50_M6_2_Portuguese"
      },
      {
        "author": "LMB Studio",
        "link_thumb": "https://live.staticflickr.com/65535/51677377034_e438e8d92a_o.gif",
        "link_bin": "https://github.com/lmbstudiocontact/mb6_2/raw/main/DragonBallAnime50_M6_2_Russian.bin",
        "name_language": "DragonBallAnime50_M6_2_Russian",
        "id_bin_language": "DragonBallAnime50_M6_2_Russian"
      },
      {
        "author": "LMB Studio",
        "link_thumb": "https://live.staticflickr.com/65535/51676951763_97e90fe59c_o.gif",
        "link_bin": "https://github.com/lmbstudiocontact/mb6_2/raw/main/DragonBallAnime50_M6_2_Spanish.bin",
        "name_language": "DragonBallAnime50_M6_2_Spanish",
        "id_bin_language": "DragonBallAnime50_M6_2_Spanish"
      }
    ],
    "array_tags": [],
    "list_album": [
      {
        "id_album": "-1148299077",
        "link_thumb": "https://live.staticflickr.com/65535/51676703881_f65d97d559_o.gif",
        "title": "Dragon Ball Anime_M6_2"
      }
    ]
  },
  {
    "author": "LMB Studio",
    "link_thumb": "https://live.staticflickr.com/65535/51677706203_fa2cbd4d29_o.gif",
    "link_bin": "https://github.com/lmbstudiocontact/mb6_9/raw/main/PokmonAnime28_M6_2.bin",
    "id_bin": "PokmonAnime28_M6_2",
    "list_language": [
      {
        "author": "LMB Studio",
        "link_thumb": "https://live.staticflickr.com/65535/51677706418_9d12728a0b_o.gif",
        "link_bin": "https://github.com/lmbstudiocontact/mb6_9/raw/main/PokmonAnime28_M6_2_English.bin",
        "name_language": "PokmonAnime28_M6_2_English",
        "id_bin_language": "PokmonAnime28_M6_2_English"
      },
      {
        "author": "LMB Studio",
        "link_thumb": "https://live.staticflickr.com/65535/51677460201_c3d514770a_o.gif",
        "link_bin": "https://github.com/lmbstudiocontact/mb6_9/raw/main/PokmonAnime28_M6_2_Portuguese.bin",
        "name_language": "PokmonAnime28_M6_2_Portuguese",
        "id_bin_language": "PokmonAnime28_M6_2_Portuguese"
      },
      {
        "author": "LMB Studio",
        "link_thumb": "https://live.staticflickr.com/65535/51678339265_e234f64d87_o.gif",
        "link_bin": "https://github.com/lmbstudiocontact/mb6_9/raw/main/PokmonAnime28_M6_2_Russian.bin",
        "name_language": "PokmonAnime28_M6_2_Russian",
        "id_bin_language": "PokmonAnime28_M6_2_Russian"
      },
      {
        "author": "LMB Studio",
        "link_thumb": "https://live.staticflickr.com/65535/51678130929_9cf5411cd3_o.gif",
        "link_bin": "https://github.com/lmbstudiocontact/mb6_9/raw/main/PokmonAnime28_M6_2_Spanish.bin",
        "name_language": "PokmonAnime28_M6_2_Spanish",
        "id_bin_language": "PokmonAnime28_M6_2_Spanish"
      }
    ],
    "array_tags": [],
    "list_album": [
      {
        "id_album": "-1571020089",
        "link_thumb": "https://live.staticflickr.com/65535/51677706203_fa2cbd4d29_o.gif",
        "title": "Pokmon Anime_M6_2"
      }
    ]
  },
  {
    "author": "LMB Studio",
    "link_thumb": "https://live.staticflickr.com/65535/51677125054_96fec48738_o.gif",
    "link_bin": "https://github.com/lmbstudiocontact/mb6_8/raw/main/CuteArt33_M6_2.bin",
    "id_bin": "CuteArt33_M6_2",
    "list_language": [
      {
        "author": "LMB Studio",
        "link_thumb": "https://live.staticflickr.com/65535/51676696713_99d9d8f37e_o.gif",
        "link_bin": "https://github.com/lmbstudiocontact/mb6_8/raw/main/CuteArt33_M6_2_English.bin",
        "name_language": "CuteArt33_M6_2_English",
        "id_bin_language": "CuteArt33_M6_2_English"
      },
      {
        "author": "LMB Studio",
        "link_thumb": "https://live.staticflickr.com/65535/51676452356_d6af44e092_o.gif",
        "link_bin": "https://github.com/lmbstudiocontact/mb6_8/raw/main/CuteArt33_M6_2_Portuguese.bin",
        "name_language": "CuteArt33_M6_2_Portuguese",
        "id_bin_language": "CuteArt33_M6_2_Portuguese"
      },
      {
        "author": "LMB Studio",
        "link_thumb": "https://live.staticflickr.com/65535/51676452611_a253b1ae38_o.gif",
        "link_bin": "https://github.com/lmbstudiocontact/mb6_8/raw/main/CuteArt33_M6_2_Russian.bin",
        "name_language": "CuteArt33_M6_2_Russian",
        "id_bin_language": "CuteArt33_M6_2_Russian"
      }
    ],
    "array_tags": [],
    "list_album": [
      {
        "id_album": "195512437",
        "link_thumb": "https://live.staticflickr.com/65535/51677125054_96fec48738_o.gif",
        "title": "Cute Art_M6_2"
      }
    ]
  },
  {
    "author": "ZanarkTempest",
    "link_thumb": "https://live.staticflickr.com/65535/51669597686_4f193c644f_o.gif",
    "link_bin": "https://github.com/lmbstudiocontact/mb6_1/raw/main/2028.bin",
    "id_bin": "2028",
    "list_language": [],
    "array_tags": [
      "power",
      "anime"
    ],
    "list_album": [
      {
        "id_album": "63410260",
        "link_thumb": "https://live.staticflickr.com/65535/51669597686_4f193c644f_o.gif",
        "title": "Anime"
      }
    ]
  },
  {
    "author": "Warley",
    "link_thumb": "https://live.staticflickr.com/65535/51670057888_44684b6766_o.gif",
    "link_bin": "https://github.com/lmbstudiocontact/mb6_1/raw/main/959.bin",
    "id_bin": "959",
    "list_language": [],
    "array_tags": [
      "digital",
      "modern",
      "digi",
      "simple",
      "battery"
    ],
    "list_album": [
      {
        "id_album": "2433880",
        "link_thumb": "https://live.staticflickr.com/65535/51670057888_44684b6766_o.gif",
        "title": "None"
      }
    ]
  },
  {
    "author": "wang0311",
    "link_thumb": "https://live.staticflickr.com/65535/51669461601_033d46ebb9_o.gif",
    "link_bin": "https://github.com/lmbstudiocontact/mb6_0/raw/main/1020.bin",
    "id_bin": "1020",
    "list_language": [],
    "array_tags": [
      "digital",
      "date",
      "analog",
      "battery"
    ],
    "list_album": [
      {
        "id_album": "2433880",
        "link_thumb": "https://live.staticflickr.com/65535/51669461601_033d46ebb9_o.gif",
        "title": "None"
      }
    ]
  },
  {
    "author": "LMB Studio",
    "link_thumb": "https://live.staticflickr.com/65535/51677914490_0d5d584ffd_o.gif",
    "link_bin": "https://github.com/lmbstudiocontact/mb6_7/raw/main/Kitty\u0026MyMelody55_M6_2.bin",
    "id_bin": "Kitty\u0026MyMelody55_M6_2",
    "list_language": [
      {
        "author": "LMB Studio",
        "link_thumb": "https://live.staticflickr.com/65535/51677279498_f378edab71_o.gif",
        "link_bin": "https://github.com/lmbstudiocontact/mb6_7/raw/main/Kitty\u0026MyMelody55_M6_2_English.bin",
        "name_language": "Kitty\u0026MyMelody55_M6_2_English",
        "id_bin_language": "Kitty\u0026MyMelody55_M6_2_English"
      },
      {
        "author": "LMB Studio",
        "link_thumb": "https://live.staticflickr.com/65535/51677032626_e7ed32ae43_o.gif",
        "link_bin": "https://github.com/lmbstudiocontact/mb6_7/raw/main/Kitty\u0026MyMelody55_M6_2_Portuguese.bin",
        "name_language": "Kitty\u0026MyMelody55_M6_2_Portuguese",
        "id_bin_language": "Kitty\u0026MyMelody55_M6_2_Portuguese"
      },
      {
        "author": "LMB Studio",
        "link_thumb": "https://live.staticflickr.com/65535/51677704969_d04ec7b616_o.gif",
        "link_bin": "https://github.com/lmbstudiocontact/mb6_7/raw/main/Kitty\u0026MyMelody55_M6_2_Russian.bin",
        "name_language": "Kitty\u0026MyMelody55_M6_2_Russian",
        "id_bin_language": "Kitty\u0026MyMelody55_M6_2_Russian"
      },
      {
        "author": "LMB Studio",
        "link_thumb": "https://live.staticflickr.com/65535/51677280208_9944e377c0_o.gif",
        "link_bin": "https://github.com/lmbstudiocontact/mb6_7/raw/main/Kitty\u0026MyMelody55_M6_2_Spanish.bin",
        "name_language": "Kitty\u0026MyMelody55_M6_2_Spanish",
        "id_bin_language": "Kitty\u0026MyMelody55_M6_2_Spanish"
      }
    ],
    "array_tags": [],
    "list_album": [
      {
        "id_album": "1352454006",
        "link_thumb": "https://live.staticflickr.com/65535/51677914490_0d5d584ffd_o.gif",
        "title": "Kitty \u0026 My Melody_M6_2"
      }
    ]
  },
  {
    "author": "ZanarkTempest",
    "link_thumb": "https://live.staticflickr.com/65535/51668769702_ae96c7679b_o.gif",
    "link_bin": "https://github.com/lmbstudiocontact/mb6_1/raw/main/1833.bin",
    "id_bin": "1833",
    "list_language": [],
    "array_tags": [
      "komisan",
      "anime"
    ],
    "list_album": [
      {
        "id_album": "63410260",
        "link_thumb": "https://live.staticflickr.com/65535/51668769702_ae96c7679b_o.gif",
        "title": "Anime"
      }
    ]
  },
  {
    "author": "zantfaul",
    "link_thumb": "https://live.staticflickr.com/65535/51670609525_764528cd8d_o.gif",
    "link_bin": "https://github.com/lmbstudiocontact/mb6_0/raw/main/541.bin",
    "id_bin": "541",
    "list_language": [],
    "array_tags": [
      "digital",
      "month",
      "english",
      "day"
    ],
    "list_album": [
      {
        "id_album": "2433880",
        "link_thumb": "https://live.staticflickr.com/65535/51670609525_764528cd8d_o.gif",
        "title": "None"
      }
    ]
  },
  {
    "author": "ZanarkTempest",
    "link_thumb": "https://live.staticflickr.com/65535/51670252644_7c9419e1c9_o.gif",
    "link_bin": "https://github.com/lmbstudiocontact/mb6_1/raw/main/1818.bin",
    "id_bin": "1818",
    "list_language": [],
    "array_tags": [
      "sonic",
      "shadow",
      "cartoon",
      "sega"
    ],
    "list_album": [
      {
        "id_album": "-2075887794",
        "link_thumb": "https://live.staticflickr.com/65535/51670252644_7c9419e1c9_o.gif",
        "title": "Cartoon"
      }
    ]
  },
  {
    "author": "raxdata",
    "link_thumb": "https://live.staticflickr.com/65535/51668935167_86abeb8098_o.gif",
    "link_bin": "https://github.com/lmbstudiocontact/mb6_0/raw/main/551.bin",
    "id_bin": "551",
    "list_language": [],
    "array_tags": [
      "date",
      "digital",
      "distance",
      "battery"
    ],
    "list_album": [
      {
        "id_album": "63410260",
        "link_thumb": "https://live.staticflickr.com/65535/51668935167_86abeb8098_o.gif",
        "title": "Anime"
      }
    ]
  },
  {
    "author": "",
    "link_thumb": "https://live.staticflickr.com/65535/51669751468_cd5ebec16a_o.gif",
    "link_bin": "https://github.com/lmbstudiocontact/mb6_0/raw/main/1429.bin",
    "id_bin": "1429",
    "list_language": [],
    "array_tags": [
      "digital",
      "date",
      "distance",
      "heartrate",
      "weather",
      "calories",
      "battery",
      "steps"
    ],
    "list_album": [
      {
        "id_album": "2433880",
        "link_thumb": "https://live.staticflickr.com/65535/51669751468_cd5ebec16a_o.gif",
        "title": "None"
      }
    ]
  },
  {
    "author": "LMB Studio",
    "link_thumb": "https://live.staticflickr.com/65535/51677320218_9d3e454d80_o.gif",
    "link_bin": "https://github.com/lmbstudiocontact/mb6_7/raw/main/Lilo\u0026StitchCartoon19_M6_2.bin",
    "id_bin": "Lilo\u0026StitchCartoon19_M6_2",
    "list_language": [
      {
        "author": "LMB Studio",
        "link_thumb": "https://live.staticflickr.com/65535/51676268867_8c6e8de328_o.gif",
        "link_bin": "https://github.com/lmbstudiocontact/mb6_7/raw/main/Lilo\u0026StitchCartoon19_M6_2_English.bin",
        "name_language": "Lilo\u0026StitchCartoon19_M6_2_English",
        "id_bin_language": "Lilo\u0026StitchCartoon19_M6_2_English"
      },
      {
        "author": "LMB Studio",
        "link_thumb": "https://live.staticflickr.com/65535/51677745769_2761745fb1_o.gif",
        "link_bin": "https://github.com/lmbstudiocontact/mb6_7/raw/main/Lilo\u0026StitchCartoon19_M6_2_Portuguese.bin",
        "name_language": "Lilo\u0026StitchCartoon19_M6_2_Portuguese",
        "id_bin_language": "Lilo\u0026StitchCartoon19_M6_2_Portuguese"
      },
      {
        "author": "LMB Studio",
        "link_thumb": "https://live.staticflickr.com/65535/51677955230_9c68956805_o.gif",
        "link_bin": "https://github.com/lmbstudiocontact/mb6_7/raw/main/Lilo\u0026StitchCartoon19_M6_2_Russian.bin",
        "name_language": "Lilo\u0026StitchCartoon19_M6_2_Russian",
        "id_bin_language": "Lilo\u0026StitchCartoon19_M6_2_Russian"
      },
      {
        "author": "LMB Studio",
        "link_thumb": "https://live.staticflickr.com/65535/51676269447_4e12c4ddde_o.gif",
        "link_bin": "https://github.com/lmbstudiocontact/mb6_7/raw/main/Lilo\u0026StitchCartoon19_M6_2_Spanish.bin",
        "name_language": "Lilo\u0026StitchCartoon19_M6_2_Spanish",
        "id_bin_language": "Lilo\u0026StitchCartoon19_M6_2_Spanish"
      }
    ],
    "array_tags": [],
    "list_album": [
      {
        "id_album": "1677497602",
        "link_thumb": "https://live.staticflickr.com/65535/51677320218_9d3e454d80_o.gif",
        "title": "Lilo \u0026 Stitch Cartoon_M6_2"
      }
    ]
  },
  {
    "author": "LMB Studio",
    "link_thumb": "https://live.staticflickr.com/65535/51677404141_9ae8610744_o.gif",
    "link_bin": "https://github.com/lmbstudiocontact/mb6_3/raw/main/PandaArt3_M6_2.bin",
    "id_bin": "PandaArt3_M6_2",
    "list_language": [
      {
        "author": "LMB Studio",
        "link_thumb": "https://live.staticflickr.com/65535/51678075154_c7b851577e_o.gif",
        "link_bin": "https://github.com/lmbstudiocontact/mb6_3/raw/main/PandaArt3_M6_2_English.bin",
        "name_language": "PandaArt3_M6_2_English",
        "id_bin_language": "PandaArt3_M6_2_English"
      },
      {
        "author": "LMB Studio",
        "link_thumb": "https://live.staticflickr.com/65535/51678284115_e5f6ce5eab_o.gif",
        "link_bin": "https://github.com/lmbstudiocontact/mb6_3/raw/main/PandaArt3_M6_2_Portuguese.bin",
        "name_language": "PandaArt3_M6_2_Portuguese",
        "id_bin_language": "PandaArt3_M6_2_Portuguese"
      },
      {
        "author": "LMB Studio",
        "link_thumb": "https://live.staticflickr.com/65535/51676597597_f145df085d_o.gif",
        "link_bin": "https://github.com/lmbstudiocontact/mb6_3/raw/main/PandaArt3_M6_2_Russian.bin",
        "name_language": "PandaArt3_M6_2_Russian",
        "id_bin_language": "PandaArt3_M6_2_Russian"
      },
      {
        "author": "LMB Studio",
        "link_thumb": "https://live.staticflickr.com/65535/51678284590_07c984f4eb_o.gif",
        "link_bin": "https://github.com/lmbstudiocontact/mb6_3/raw/main/PandaArt3_M6_2_Spanish.bin",
        "name_language": "PandaArt3_M6_2_Spanish",
        "id_bin_language": "PandaArt3_M6_2_Spanish"
      }
    ],
    "array_tags": [],
    "list_album": [
      {
        "id_album": "1057265438",
        "link_thumb": "https://live.staticflickr.com/65535/51677404141_9ae8610744_o.gif",
        "title": "Panda Art_M6_2"
      }
    ]
  },
  {
    "author": "13hakta",
    "link_thumb": "https://live.staticflickr.com/65535/51668684537_dbaf78ecf4_o.gif",
    "link_bin": "https://github.com/lmbstudiocontact/mb6_0/raw/main/121.bin",
    "id_bin": "121",
    "list_language": [],
    "array_tags": [
      "digital",
      "date",
      "distance",
      "heartrate",
      "weather",
      "battery",
      "steps",
      "status"
    ],
    "list_album": [
      {
        "id_album": "2433880",
        "link_thumb": "https://live.staticflickr.com/65535/51668684537_dbaf78ecf4_o.gif",
        "title": "None"
      }
    ]
  }
]